Workbook

Sheet START HERE
A1: EXCEL CAPSTONE PROJECT — Q1 2026 BUSINESS PERFORMANCE REPORT
A2: Prepared for: Anotida Kanzara | B2: Level: Intermediate
A4: YOUR MISSION
A5: The CEO needs a board-ready report by Friday. You have 4 messy data sheets.
A6: Complete every task below in order.
A8: SHEET | B8: TASK | C8: SKILLS APPLIED
A9: RAW SALES DATA | B9: 1. Remove duplicate transactions 2. Standardise Branch, Region & Status columns 3. Fix mixed date formats 4. Remove extra spaces from Rep names 5. Fix 3 blank customer names 6. Fix 'N/A' and 'TBC' in Revenue column 7. Correct 4 wrong revenue calculations 8. Flag negative quantities (returns) 9. Add Revenue Check column (Qty × Price) 10. Add IFERROR() around any broken formulas | C9: Data Cleaning: TRIM, PROPER, Find & Replace, IFERROR, Remove Duplicates
A10: PRODUCT CATALOGUE | B10: 11. Use XLOOKUP to pull Product Name, Category and Cost Price into Sales sheet 12. Add a Profit column (Revenue - Cost) 13. Add a Profit Margin % column | C10: XLOOKUP (absolute refs), Calculated Columns
A11: STAFF TABLE | B11: 14. Use XLOOKUP to pull Rep Name, Branch and Commission Rate into Sales sheet 15. Add Commission Earned column (Revenue × Rate) 16. Add a Performance Flag: 'Star' if Revenue >R20,000, else 'Standard' | C11: XLOOKUP, IF statements
A12: CLEANED DATA | B12: 17. Paste all cleaned and enriched data here 18. Format as Excel Table (Ctrl+T) 19. Apply currency formatting to all money columns 20. Freeze top row | C12: Table formatting, Number formatting
A13: REPORT SHEET | B13: 21. Build PivotTable 1: Revenue by Branch 22. Build PivotTable 2: Revenue by Product Category 23. Build PivotTable 3: Top Sales Reps 24. Build PivotTable 4: Revenue by Month 25. Create Bar Chart from PivotTable 1 26. Create Pie Chart from PivotTable 2 27. Create sorted Bar Chart from PivotTable 3 28. Create Line Chart from PivotTable 4 29. Fill in the Executive Summary section 30. Add Slicers to filter by Branch and Month | C13: PivotTables, Charts, Slicers
A15: STRETCH CHALLENGES (BONUS)
A16: Add a COUNTIF to count how many orders each branch placed
A17: Use AVERAGEIF to find average order value per region
A18: Add conditional formatting: top 10% revenue rows in green, bottom 10% in red
A19: Add a dropdown validation list for the Status column

Sheet PRODUCT CATALOGUE
A1: ProductID | B1: Product Name | C1: Category | D1: Unit Price (R) | E1: Cost Price (R) | F1: Supplier
A2: PR01 | B2: Gaming Laptop | C2: Electronics | D2: 15000 | E2: 9800 | F2: TechSource SA
A3: PR02 | B3: Office Chair | C3: Furniture | D3: 3200 | E3: 1750 | F3: FurniPro
A4: PR03 | B4: Wireless Headset | C4: Electronics | D4: 1800 | E4: 950 | F4: TechSource SA
A5: PR04 | B5: Standing Desk | C5: Furniture | D5: 5500 | E5: 3100 | F5: FurniPro
A6: PR05 | B6: Webcam HD | C6: Electronics | D6: 1200 | E6: 620 | F6: TechSource SA
A7: PR06 | B7: Notebook Bundle | C7: Stationery | D7: 350 | E7: 140 | F7: PaperWorks
A8: PR07 | B8: Mechanical Keyboard | C8: Electronics | D8: 2100 | E8: 1100 | F8: TechSource SA
A9: PR08 | B9: Whiteboard | C9: Stationery | D9: 890 | E9: 420 | F9: PaperWorks
A10: PR09 | B10: Monitor 27inch | C10: Electronics | D10: 4800 | E10: 2900 | F10: TechSource SA
A11: PR10 | B11: Ergonomic Mouse | C11: Electronics | D11: 650 | E11: 310 | F11: TechSource SA
A12: PR11 | B12: Filing Cabinet | C12: Furniture | D12: 2800 | E12: 1600 | F12: FurniPro
A13: PR12 | B13: Printer Paper Ream | C13: Stationery | D13: 120 | E13: 55 | F13: PaperWorks

Sheet STAFF TABLE
A1: EmpID | B1: Rep Name | C1: Branch | D1: Region | E1: Commission Rate | F1: Target (R)
A2: EM01 | B2: Thabo Nkosi | C2: Sandton Branch | D2: Gauteng | E2: 0.08 | F2: 80000
A3: EM02 | B3: Priya Pillay | C3: Durban Branch | D3: KZN | E3: 0.1 | F3: 75000
A4: EM03 | B4: Zanele Dlamini | C4: Cape Town Branch | D4: Western Cape | E4: 0.09 | F4: 85000
A5: EM04 | B5: Riaan Botha | C5: Sandton Branch | D5: Gauteng | E5: 0.08 | F5: 80000
A6: EM05 | B6: Amahle Zulu | C6: Durban Branch | D6: KZN | E6: 0.1 | F6: 75000
A7: EM06 | B7: Lebo Mahlangu | C7: Polokwane Branch | D7: Limpopo | E7: 0.07 | F7: 60000
A8: EM07 | B8: Fatima Patel | C8: Cape Town Branch | D8: Western Cape | E8: 0.09 | F8: 85000
A9: EM08 | B9: Kefilwe Sithole | C9: Sandton Branch | D9: Gauteng | E9: 0.08 | F9: 80000
A10: EM09 | B10: David Moyo | C10: Polokwane Branch | D10: Limpopo | E10: 0.07 | F10: 60000
A11: EM10 | B11: Sipho Dlamini | C11: Durban Branch | D11: KZN | E11: 0.1 | F11: 75000

Sheet RAW SALES DATA
A1: TxnID | B1: Date | C1: EmpID | D1: ProductID | E1: CustomerName | F1: Quantity | G1: Unit Price (R) | H1: Total Revenue (R) | I1: Status | J1: Rep Name ← XLOOKUP | K1: Branch | L1: Region | M1: Commission Rate | N1: Product Name ← XLOOKUP | O1: Category | P1: Cost Price (R) | Q1: Revenue Check ← CALCULATE | R1: Profit (R) | S1: Profit Margin % | T1: Commission Earned (R) | U1: Performance Flag
A2: TXN001 | B2: 2026-01-05 | C2: EM01 | D2: PR09 | E2: Fatima Patel | F2: 2 | G2: 4800 | H2: 9600 | I2: COMPLETED | J2: =_xlfn.XLOOKUP(C2,'STAFF TABLE'!A2:A11,'STAFF TABLE'!B2:B11) -> Thabo Nkosi | K2: =_xlfn.XLOOKUP(C2,'STAFF TABLE'!$A$2:$A$11,'STAFF TABLE'!$C$2:$C$11) -> Sandton Branch | L2: =_xlfn.XLOOKUP(C2,'STAFF TABLE'!$A$2:$A$11,'STAFF TABLE'!$D$2:$D$11) -> Gauteng | M2: =_xlfn.XLOOKUP(C2,'STAFF TABLE'!$A$2:$A$11,'STAFF TABLE'!$E$2:$E$11) -> 0.08 | N2: =_xlfn.XLOOKUP(D2,'PRODUCT CATALOGUE'!$A$2:$A$13,'PRODUCT CATALOGUE'!$B$2:$B$13) -> Monitor 27inch | O2: =_xlfn.XLOOKUP(D2,'PRODUCT CATALOGUE'!$A$2:$A$13,'PRODUCT CATALOGUE'!$C$2:$C$13) -> Electronics | P2: =_xlfn.XLOOKUP(D2,'PRODUCT CATALOGUE'!$A$2:$A$13,'PRODUCT CATALOGUE'!$E$2:$E$13) -> 2900 | Q2: 9600 | R2: =Q2-P2 -> 6700 | S2: =R2/Q2 -> 0.69791667 | T2: =M2*Q2 -> 768 | U2: =IF(S2>100%,"false","good") -> good
A3: TXN002 | B3: 05/01/2026 | C3: EM03 | D3: PR01 | F3: 1 | G3: 15000 | H3: 15000 | I3: COMPLETED | J3: =_xlfn.XLOOKUP(C3,'STAFF TABLE'!A3:A12,'STAFF TABLE'!B3:B12) -> Zanele Dlamini | K3: =_xlfn.XLOOKUP(C3,'STAFF TABLE'!$A$2:$A$11,'STAFF TABLE'!$C$2:$C$11) -> Cape Town Branch | L3: =_xlfn.XLOOKUP(C3,'STAFF TABLE'!$A$2:$A$11,'STAFF TABLE'!$D$2:$D$11) -> Western Cape | M3: =_xlfn.XLOOKUP(C3,'STAFF TABLE'!$A$2:$A$11,'STAFF TABLE'!$E$2:$E$11) -> 0.09 | N3: =_xlfn.XLOOKUP(D3,'PRODUCT CATALOGUE'!$A$2:$A$13,'PRODUCT CATALOGUE'!$B$2:$B$13) -> Gaming Laptop | O3: =_xlfn.XLOOKUP(D3,'PRODUCT CATALOGUE'!$A$2:$A$13,'PRODUCT CATALOGUE'!$C$2:$C$13) -> Electronics | P3: =_xlfn.XLOOKUP(D3,'PRODUCT CATALOGUE'!$A$2:$A$13,'PRODUCT CATALOGUE'!$E$2:$E$13) -> 9800 | Q3: 15000 | R3: =Q3-P3 -> 5200 | S3: =R3/Q3 -> 0.34666667 | T3: =M3*Q3 -> 1350 | U3: =IF(S3>100%,"false","good") -> good
A4: TXN003 | B4: 2026-01-06 | C4: EM05 | D4: PR07 | E4: Nomsa Khumalo | F4: 3 | G4: 2100 | H4: 6300 | I4: COMPLETED | J4: =_xlfn.XLOOKUP(C4,'STAFF TABLE'!A4:A13,'STAFF TABLE'!B4:B13) -> Amahle Zulu | K4: =_xlfn.XLOOKUP(C4,'STAFF TABLE'!$A$2:$A$11,'STAFF TABLE'!$C$2:$C$11) -> Durban Branch | L4: =_xlfn.XLOOKUP(C4,'STAFF TABLE'!$A$2:$A$11,'STAFF TABLE'!$D$2:$D$11) -> KZN | M4: =_xlfn.XLOOKUP(C4,'STAFF TABLE'!$A$2:$A$11,'STAFF TABLE'!$E$2:$E$11) -> 0.1 | N4: =_xlfn.XLOOKUP(D4,'PRODUCT CATALOGUE'!$A$2:$A$13,'PRODUCT CATALOGUE'!$B$2:$B$13) -> Mechanical Keyboard | O4: =_xlfn.XLOOKUP(D4,'PRODUCT CATALOGUE'!$A$2:$A$13,'PRODUCT CATALOGUE'!$C$2:$C$13) -> Electronics | P4: =_xlfn.XLOOKUP(D4,'PRODUCT CATALOGUE'!$A$2:$A$13,'PRODUCT CATALOGUE'!$E$2:$E$13) -> 1100 | Q4: 6300 | R4: =Q4-P4 -> 5200 | S4: =R4/Q4 -> 0.82539683 | T4: =M4*Q4 -> 630 | U4: =IF(S4>100%,"false","good") -> good
A5: TXN004 | B5: 2026-01-06 | C5: EM02 | D5: PR04 | E5: Pieter van Wyk | F5: 1 | G5: 5500 | H5: 5500 | I5: COMPLETED | J5: =_xlfn.XLOOKUP(C5,'STAFF TABLE'!A2:A11,'STAFF TABLE'!B2:B11) -> Priya Pillay | K5: =_xlfn.XLOOKUP(C5,'STAFF TABLE'!$A$2:$A$11,'STAFF TABLE'!$C$2:$C$11) -> Durban Branch | L5: =_xlfn.XLOOKUP(C5,'STAFF TABLE'!$A$2:$A$11,'STAFF TABLE'!$D$2:$D$11) -> KZN | M5: =_xlfn.XLOOKUP(C5,'STAFF TABLE'!$A$2:$A$11,'STAFF TABLE'!$E$2:$E$11) -> 0.1 | N5: =_xlfn.XLOOKUP(D5,'PRODUCT CATALOGUE'!$A$2:$A$13,'PRODUCT CATALOGUE'!$B$2:$B$13) -> Standing Desk | O5: =_xlfn.XLOOKUP(D5,'PRODUCT CATALOGUE'!$A$2:$A$13,'PRODUCT CATALOGUE'!$C$2:$C$13) -> Furniture | P5: =_xlfn.XLOOKUP(D5,'PRODUCT CATALOGUE'!$A$2:$A$13,'PRODUCT CATALOGUE'!$E$2:$E$13) -> 3100 | Q5: 5500 | R5: =Q5-P5 -> 2400 | S5: =R5/Q5 -> 0.43636364 | T5: =M5*Q5 -> 550 | U5: =IF(S5>100%,"false","good") -> good
A6: TXN005 | B6: 2026-01-07 | C6: EM08 | D6: PR06 | E6: Kefilwe Sithole | F6: 2 | G6: 350 | H6: 700 | I6: COMPLETED | J6: =_xlfn.XLOOKUP(C6,'STAFF TABLE'!A6:A15,'STAFF TABLE'!B6:B15) -> Kefilwe Sithole | K6: =_xlfn.XLOOKUP(C6,'STAFF TABLE'!$A$2:$A$11,'STAFF TABLE'!$C$2:$C$11) -> Sandton Branch | L6: =_xlfn.XLOOKUP(C6,'STAFF TABLE'!$A$2:$A$11,'STAFF TABLE'!$D$2:$D$11) -> Gauteng | M6: =_xlfn.XLOOKUP(C6,'STAFF TABLE'!$A$2:$A$11,'STAFF TABLE'!$E$2:$E$11) -> 0.08 | N6: =_xlfn.XLOOKUP(D6,'PRODUCT CATALOGUE'!$A$2:$A$13,'PRODUCT CATALOGUE'!$B$2:$B$13) -> Notebook Bundle | O6: =_xlfn.XLOOKUP(D6,'PRODUCT CATALOGUE'!$A$2:$A$13,'PRODUCT CATALOGUE'!$C$2:$C$13) -> Stationery | P6: =_xlfn.XLOOKUP(D6,'PRODUCT CATALOGUE'!$A$2:$A$13,'PRODUCT CATALOGUE'!$E$2:$E$13) -> 140 | Q6: 700 | R6: =Q6-P6 -> 560 | S6: =R6/Q6 -> 0.8 | T6: =M6*Q6 -> 56 | U6: =IF(S6>100%,"false","good") -> good
A7: TXN006 | B7: 2026-01-07 | C7: EM06 | D7: PR02 | E7: Sipho Dlamini | F7: 1 | G7: 3200 | H7: 3200 | I7: PENDING | J7: =_xlfn.XLOOKUP(C7,'STAFF TABLE'!A7:A16,'STAFF TABLE'!B7:B16) -> Lebo Mahlangu | K7: =_xlfn.XLOOKUP(C7,'STAFF TABLE'!$A$2:$A$11,'STAFF TABLE'!$C$2:$C$11) -> Polokwane Branch | L7: =_xlfn.XLOOKUP(C7,'STAFF TABLE'!$A$2:$A$11,'STAFF TABLE'!$D$2:$D$11) -> Limpopo | M7: =_xlfn.XLOOKUP(C7,'STAFF TABLE'!$A$2:$A$11,'STAFF TABLE'!$E$2:$E$11) -> 0.07 | N7: =_xlfn.XLOOKUP(D7,'PRODUCT CATALOGUE'!$A$2:$A$13,'PRODUCT CATALOGUE'!$B$2:$B$13) -> Office Chair | O7: =_xlfn.XLOOKUP(D7,'PRODUCT CATALOGUE'!$A$2:$A$13,'PRODUCT CATALOGUE'!$C$2:$C$13) -> Furniture | P7: =_xlfn.XLOOKUP(D7,'PRODUCT CATALOGUE'!$A$2:$A$13,'PRODUCT CATALOGUE'!$E$2:$E$13) -> 1750 | Q7: 3200 | R7: =Q7-P7 -> 1450 | S7: =R7/Q7 -> 0.453125 | T7: =M7*Q7 -> 224 | U7: =IF(S7>100%,"false","good") -> good
A8: TXN007 | B8: 07/01/2026 | C8: EM01 | D8: PR10 | E8: David Moyo | F8: 5 | G8: 650 | H8: 3250 | I8: COMPLETED | J8: =_xlfn.XLOOKUP(C8,'STAFF TABLE'!A2:A11,'STAFF TABLE'!B2:B11) -> Thabo Nkosi | K8: =_xlfn.XLOOKUP(C8,'STAFF TABLE'!$A$2:$A$11,'STAFF TABLE'!$C$2:$C$11) -> Sandton Branch | L8: =_xlfn.XLOOKUP(C8,'STAFF TABLE'!$A$2:$A$11,'STAFF TABLE'!$D$2:$D$11) -> Gauteng | M8: =_xlfn.XLOOKUP(C8,'STAFF TABLE'!$A$2:$A$11,'STAFF TABLE'!$E$2:$E$11) -> 0.08 | N8: =_xlfn.XLOOKUP(D8,'PRODUCT CATALOGUE'!$A$2:$A$13,'PRODUCT CATALOGUE'!$B$2:$B$13) -> Ergonomic Mouse | O8: =_xlfn.XLOOKUP(D8,'PRODUCT CATALOGUE'!$A$2:$A$13,'PRODUCT CATALOGUE'!$C$2:$C$13) -> Electronics | P8: =_xlfn.XLOOKUP(D8,'PRODUCT CATALOGUE'!$A$2:$A$13,'PRODUCT CATALOGUE'!$E$2:$E$13) -> 310 | Q8: 3250 | R8: =Q8-P8 -> 2940 | S8: =R8/Q8 -> 0.90461538 | T8: =M8*Q8 -> 260 | U8: =IF(S8>100%,"false","good") -> good
A9: TXN008 | B9: 2026-01-08 | C9: EM04 | D9: PR03 | E9: Priya Pillay | F9: 4 | G9: 1800 | H9: 7200 | I9: COMPLETED | J9: =_xlfn.XLOOKUP(C9,'STAFF TABLE'!A3:A12,'STAFF TABLE'!B3:B12) -> Riaan Botha | K9: =_xlfn.XLOOKUP(C9,'STAFF TABLE'!$A$2:$A$11,'STAFF TABLE'!$C$2:$C$11) -> Sandton Branch | L9: =_xlfn.XLOOKUP(C9,'STAFF TABLE'!$A$2:$A$11,'STAFF TABLE'!$D$2:$D$11) -> Gauteng | M9: =_xlfn.XLOOKUP(C9,'STAFF TABLE'!$A$2:$A$11,'STAFF TABLE'!$E$2:$E$11) -> 0.08 | N9: =_xlfn.XLOOKUP(D9,'PRODUCT CATALOGUE'!$A$2:$A$13,'PRODUCT CATALOGUE'!$B$2:$B$13) -> Wireless Headset | O9: =_xlfn.XLOOKUP(D9,'PRODUCT CATALOGUE'!$A$2:$A$13,'PRODUCT CATALOGUE'!$C$2:$C$13) -> Electronics | P9: =_xlfn.XLOOKUP(D9,'PRODUCT CATALOGUE'!$A$2:$A$13,'PRODUCT CATALOGUE'!$E$2:$E$13) -> 950 | Q9: 7200 | R9: =Q9-P9 -> 6250 | S9: =R9/Q9 -> 0.86805556 | T9: =M9*Q9 -> 576 | U9: =IF(S9>100%,"false","good") -> good
A10: TXN009 | B10: 2026-01-08 | C10: EM07 | D10: PR01 | E10: Zanele Mokoena | F10: 2 | G10: 15000 | H10: 25000 | I10: COMPLETED | J10: =_xlfn.XLOOKUP(C10,'STAFF TABLE'!A4:A13,'STAFF TABLE'!B4:B13) -> Fatima Patel | K10: =_xlfn.XLOOKUP(C10,'STAFF TABLE'!$A$2:$A$11,'STAFF TABLE'!$C$2:$C$11) -> Cape Town Branch | L10: =_xlfn.XLOOKUP(C10,'STAFF TABLE'!$A$2:$A$11,'STAFF TABLE'!$D$2:$D$11) -> Western Cape | M10: =_xlfn.XLOOKUP(C10,'STAFF TABLE'!$A$2:$A$11,'STAFF TABLE'!$E$2:$E$11) -> 0.09 | N10: =_xlfn.XLOOKUP(D10,'PRODUCT CATALOGUE'!$A$2:$A$13,'PRODUCT CATALOGUE'!$B$2:$B$13) -> Gaming Laptop | O10: =_xlfn.XLOOKUP(D10,'PRODUCT CATALOGUE'!$A$2:$A$13,'PRODUCT CATALOGUE'!$C$2:$C$13) -> Electronics | P10: =_xlfn.XLOOKUP(D10,'PRODUCT CATALOGUE'!$A$2:$A$13,'PRODUCT CATALOGUE'!$E$2:$E$13) -> 9800 | Q10: 30000 | R10: =Q10-P10 -> 20200 | S10: =R10/Q10 -> 0.67333333 | T10: =M10*Q10 -> 2700 | U10: =IF(S10>100%,"false","good") -> good
A11: TXN010 | B11: 2026-01-09 | C11: EM10 | D11: PR08 | F11: 3 | G11: 890 | H11: 2670 | I11: CANCELLED | J11: =_xlfn.XLOOKUP(C11,'STAFF TABLE'!A5:A14,'STAFF TABLE'!B5:B14) -> Sipho Dlamini | K11: =_xlfn.XLOOKUP(C11,'STAFF TABLE'!$A$2:$A$11,'STAFF TABLE'!$C$2:$C$11) -> Durban Branch | L11: =_xlfn.XLOOKUP(C11,'STAFF TABLE'!$A$2:$A$11,'STAFF TABLE'!$D$2:$D$11) -> KZN | M11: =_xlfn.XLOOKUP(C11,'STAFF TABLE'!$A$2:$A$11,'STAFF TABLE'!$E$2:$E$11) -> 0.1 | N11: =_xlfn.XLOOKUP(D11,'PRODUCT CATALOGUE'!$A$2:$A$13,'PRODUCT CATALOGUE'!$B$2:$B$13) -> Whiteboard | O11: =_xlfn.XLOOKUP(D11,'PRODUCT CATALOGUE'!$A$2:$A$13,'PRODUCT CATALOGUE'!$C$2:$C$13) -> Stationery | P11: =_xlfn.XLOOKUP(D11,'PRODUCT CATALOGUE'!$A$2:$A$13,'PRODUCT CATALOGUE'!$E$2:$E$13) -> 420 | Q11: 2670 | R11: =Q11-P11 -> 2250 | S11: =R11/Q11 -> 0.84269663 | T11: =M11*Q11 -> 267 | U11: =IF(S11>100%,"false","good") -> good
A12: TXN011 | B12: 2026-01-09 | C12: EM03 | D12: PR09 | E12: Riaan Botha | F12: 1 | G12: 4800 | H12: 4800 | I12: COMPLETED | J12: =_xlfn.XLOOKUP(C12,'STAFF TABLE'!A2:A11,'STAFF TABLE'!B2:B11) -> Zanele Dlamini | K12: =_xlfn.XLOOKUP(C12,'STAFF TABLE'!$A$2:$A$11,'STAFF TABLE'!$C$2:$C$11) -> Cape Town Branch | L12: =_xlfn.XLOOKUP(C12,'STAFF TABLE'!$A$2:$A$11,'STAFF TABLE'!$D$2:$D$11) -> Western Cape | M12: =_xlfn.XLOOKUP(C12,'STAFF TABLE'!$A$2:$A$11,'STAFF TABLE'!$E$2:$E$11) -> 0.09 | N12: =_xlfn.XLOOKUP(D12,'PRODUCT CATALOGUE'!$A$2:$A$13,'PRODUCT CATALOGUE'!$B$2:$B$13) -> Monitor 27inch | O12: =_xlfn.XLOOKUP(D12,'PRODUCT CATALOGUE'!$A$2:$A$13,'PRODUCT CATALOGUE'!$C$2:$C$13) -> Electronics | P12: =_xlfn.XLOOKUP(D12,'PRODUCT CATALOGUE'!$A$2:$A$13,'PRODUCT CATALOGUE'!$E$2:$E$13) -> 2900 | Q12: 4800 | R12: =Q12-P12 -> 1900 | S12: =R12/Q12 -> 0.39583333 | T12: =M12*Q12 -> 432 | U12: =IF(S12>100%,"false","good") -> good
A13: TXN012 | B13: 09/01/2026 | C13: EM05 | D13: PR12 | E13: Amahle Zulu | F13: 10 | G13: 120 | H13: 1200 | I13: COMPLETED | J13: =_xlfn.XLOOKUP(C13,'STAFF TABLE'!A3:A12,'STAFF TABLE'!B3:B12) -> Amahle Zulu | K13: =_xlfn.XLOOKUP(C13,'STAFF TABLE'!$A$2:$A$11,'STAFF TABLE'!$C$2:$C$11) -> Durban Branch | L13: =_xlfn.XLOOKUP(C13,'STAFF TABLE'!$A$2:$A$11,'STAFF TABLE'!$D$2:$D$11) -> KZN | M13: =_xlfn.XLOOKUP(C13,'STAFF TABLE'!$A$2:$A$11,'STAFF TABLE'!$E$2:$E$11) -> 0.1 | N13: =_xlfn.XLOOKUP(D13,'PRODUCT CATALOGUE'!$A$2:$A$13,'PRODUCT CATALOGUE'!$B$2:$B$13) -> Printer Paper Ream | O13: =_xlfn.XLOOKUP(D13,'PRODUCT CATALOGUE'!$A$2:$A$13,'PRODUCT CATALOGUE'!$C$2:$C$13) -> Stationery | P13: =_xlfn.XLOOKUP(D13,'PRODUCT CATALOGUE'!$A$2:$A$13,'PRODUCT CATALOGUE'!$E$2:$E$13) -> 55 | Q13: 1200 | R13: =Q13-P13 -> 1145 | S13: =R13/Q13 -> 0.95416667 | T13: =M13*Q13 -> 120 | U13: =IF(S13>100%,"false","good") -> good
A14: TXN013 | B14: 2026-01-10 | C14: EM09 | D14: PR11 | E14: Lebo Mahlangu | F14: 1 | G14: 2800 | H14: 2800 | I14: COMPLETED | J14: =_xlfn.XLOOKUP(C14,'STAFF TABLE'!A4:A13,'STAFF TABLE'!B4:B13) -> David Moyo | K14: =_xlfn.XLOOKUP(C14,'STAFF TABLE'!$A$2:$A$11,'STAFF TABLE'!$C$2:$C$11) -> Polokwane Branch | L14: =_xlfn.XLOOKUP(C14,'STAFF TABLE'!$A$2:$A$11,'STAFF TABLE'!$D$2:$D$11) -> Limpopo | M14: =_xlfn.XLOOKUP(C14,'STAFF TABLE'!$A$2:$A$11,'STAFF TABLE'!$E$2:$E$11) -> 0.07 | N14: =_xlfn.XLOOKUP(D14,'PRODUCT CATALOGUE'!$A$2:$A$13,'PRODUCT CATALOGUE'!$B$2:$B$13) -> Filing Cabinet | O14: =_xlfn.XLOOKUP(D14,'PRODUCT CATALOGUE'!$A$2:$A$13,'PRODUCT CATALOGUE'!$C$2:$C$13) -> Furniture | P14: =_xlfn.XLOOKUP(D14,'PRODUCT CATALOGUE'!$A$2:$A$13,'PRODUCT CATALOGUE'!$E$2:$E$13) -> 1600 | Q14: 2800 | R14: =Q14-P14 -> 1200 | S14: =R14/Q14 -> 0.42857143 | T14: =M14*Q14 -> 196 | U14: =IF(S14>100%,"false","good") -> good
A15: TXN014 | B15: 2026-01-10 | C15: EM02 | D15: PR05 | E15: Fatima Patel | F15: 4 | G15: 1200 | H15: 4800 | I15: COMPLETED | J15: =_xlfn.XLOOKUP(C15,'STAFF TABLE'!A2:A11,'STAFF TABLE'!B2:B11) -> Priya Pillay | K15: =_xlfn.XLOOKUP(C15,'STAFF TABLE'!$A$2:$A$11,'STAFF TABLE'!$C$2:$C$11) -> Durban Branch | L15: =_xlfn.XLOOKUP(C15,'STAFF TABLE'!$A$2:$A$11,'STAFF TABLE'!$D$2:$D$11) -> KZN | M15: =_xlfn.XLOOKUP(C15,'STAFF TABLE'!$A$2:$A$11,'STAFF TABLE'!$E$2:$E$11) -> 0.1 | N15: =_xlfn.XLOOKUP(D15,'PRODUCT CATALOGUE'!$A$2:$A$13,'PRODUCT CATALOGUE'!$B$2:$B$13) -> Webcam HD | O15: =_xlfn.XLOOKUP(D15,'PRODUCT CATALOGUE'!$A$2:$A$13,'PRODUCT CATALOGUE'!$C$2:$C$13) -> Electronics | P15: =_xlfn.XLOOKUP(D15,'PRODUCT CATALOGUE'!$A$2:$A$13,'PRODUCT CATALOGUE'!$E$2:$E$13) -> 620 | Q15: 4800 | R15: =Q15-P15 -> 4180 | S15: =R15/Q15 -> 0.87083333 | T15: =M15*Q15 -> 480 | U15: =IF(S15>100%,"false","good") -> good
A16: TXN015 | B16: 2026-01-11 | C16: EM08 | D16: PR01 | E16: Nomsa Khumalo | F16: 1 | G16: 15000 | H16: 15000 | I16: COMPLETED | J16: =_xlfn.XLOOKUP(C16,'STAFF TABLE'!A6:A15,'STAFF TABLE'!B6:B15) -> Kefilwe Sithole | K16: =_xlfn.XLOOKUP(C16,'STAFF TABLE'!$A$2:$A$11,'STAFF TABLE'!$C$2:$C$11) -> Sandton Branch | L16: =_xlfn.XLOOKUP(C16,'STAFF TABLE'!$A$2:$A$11,'STAFF TABLE'!$D$2:$D$11) -> Gauteng | M16: =_xlfn.XLOOKUP(C16,'STAFF TABLE'!$A$2:$A$11,'STAFF TABLE'!$E$2:$E$11) -> 0.08 | N16: =_xlfn.XLOOKUP(D16,'PRODUCT CATALOGUE'!$A$2:$A$13,'PRODUCT CATALOGUE'!$B$2:$B$13) -> Gaming Laptop | O16: =_xlfn.XLOOKUP(D16,'PRODUCT CATALOGUE'!$A$2:$A$13,'PRODUCT CATALOGUE'!$C$2:$C$13) -> Electronics | P16: =_xlfn.XLOOKUP(D16,'PRODUCT CATALOGUE'!$A$2:$A$13,'PRODUCT CATALOGUE'!$E$2:$E$13) -> 9800 | Q16: 15000 | R16: =Q16-P16 -> 5200 | S16: =R16/Q16 -> 0.34666667 | T16: =M16*Q16 -> 1200 | U16: =IF(S16>100%,"false","good") -> good
A17: TXN016 | B17: 2026-01-12 | C17: EM04 | D17: PR04 | E17: Pieter van Wyk | F17: 1 | G17: 5500 | H17: 5500 | I17: COMPLETED | J17: =_xlfn.XLOOKUP(C17,'STAFF TABLE'!A2:A11,'STAFF TABLE'!B2:B11) -> Riaan Botha | K17: =_xlfn.XLOOKUP(C17,'STAFF TABLE'!$A$2:$A$11,'STAFF TABLE'!$C$2:$C$11) -> Sandton Branch | L17: =_xlfn.XLOOKUP(C17,'STAFF TABLE'!$A$2:$A$11,'STAFF TABLE'!$D$2:$D$11) -> Gauteng | M17: =_xlfn.XLOOKUP(C17,'STAFF TABLE'!$A$2:$A$11,'STAFF TABLE'!$E$2:$E$11) -> 0.08 | N17: =_xlfn.XLOOKUP(D17,'PRODUCT CATALOGUE'!$A$2:$A$13,'PRODUCT CATALOGUE'!$B$2:$B$13) -> Standing Desk | O17: =_xlfn.XLOOKUP(D17,'PRODUCT CATALOGUE'!$A$2:$A$13,'PRODUCT CATALOGUE'!$C$2:$C$13) -> Furniture | P17: =_xlfn.XLOOKUP(D17,'PRODUCT CATALOGUE'!$A$2:$A$13,'PRODUCT CATALOGUE'!$E$2:$E$13) -> 3100 | Q17: 5500 | R17: =Q17-P17 -> 2400 | S17: =R17/Q17 -> 0.43636364 | T17: =M17*Q17 -> 440 | U17: =IF(S17>100%,"false","good") -> good
A18: TXN017 | B18: 12/01/2026 | C18: EM06 | D18: PR07 | E18: Kefilwe Sithole | F18: -1 | G18: 2100 | I18: RETURNED | J18: =_xlfn.XLOOKUP(C18,'STAFF TABLE'!A3:A12,'STAFF TABLE'!B3:B12) -> Lebo Mahlangu | K18: =_xlfn.XLOOKUP(C18,'STAFF TABLE'!$A$2:$A$11,'STAFF TABLE'!$C$2:$C$11) -> Polokwane Branch | L18: =_xlfn.XLOOKUP(C18,'STAFF TABLE'!$A$2:$A$11,'STAFF TABLE'!$D$2:$D$11) -> Limpopo | M18: =_xlfn.XLOOKUP(C18,'STAFF TABLE'!$A$2:$A$11,'STAFF TABLE'!$E$2:$E$11) -> 0.07 | N18: =_xlfn.XLOOKUP(D18,'PRODUCT CATALOGUE'!$A$2:$A$13,'PRODUCT CATALOGUE'!$B$2:$B$13) -> Mechanical Keyboard | O18: =_xlfn.XLOOKUP(D18,'PRODUCT CATALOGUE'!$A$2:$A$13,'PRODUCT CATALOGUE'!$C$2:$C$13) -> Electronics | P18: =_xlfn.XLOOKUP(D18,'PRODUCT CATALOGUE'!$A$2:$A$13,'PRODUCT CATALOGUE'!$E$2:$E$13) -> 1100 | Q18: -2100 | R18: =Q18-P18 -> -3200 | S18: =R18/Q18 -> 1.5238095 | T18: =M18*Q18 -> -147 | U18: =IF(S18>100%,"false","good") -> false
A19: TXN018 | B19: 2026-01-13 | C19: EM01 | D19: PR06 | F19: 15 | G19: 350 | H19: 5250 | I19: COMPLETED | J19: =_xlfn.XLOOKUP(C19,'STAFF TABLE'!A2:A11,'STAFF TABLE'!B2:B11) -> Thabo Nkosi | K19: =_xlfn.XLOOKUP(C19,'STAFF TABLE'!$A$2:$A$11,'STAFF TABLE'!$C$2:$C$11) -> Sandton Branch | L19: =_xlfn.XLOOKUP(C19,'STAFF TABLE'!$A$2:$A$11,'STAFF TABLE'!$D$2:$D$11) -> Gauteng | M19: =_xlfn.XLOOKUP(C19,'STAFF TABLE'!$A$2:$A$11,'STAFF TABLE'!$E$2:$E$11) -> 0.08 | N19: =_xlfn.XLOOKUP(D19,'PRODUCT CATALOGUE'!$A$2:$A$13,'PRODUCT CATALOGUE'!$B$2:$B$13) -> Notebook Bundle | O19: =_xlfn.XLOOKUP(D19,'PRODUCT CATALOGUE'!$A$2:$A$13,'PRODUCT CATALOGUE'!$C$2:$C$13) -> Stationery | P19: =_xlfn.XLOOKUP(D19,'PRODUCT CATALOGUE'!$A$2:$A$13,'PRODUCT CATALOGUE'!$E$2:$E$13) -> 140 | Q19: 5250 | R19: =Q19-P19 -> 5110 | S19: =R19/Q19 -> 0.97333333 | T19: =M19*Q19 -> 420 | U19: =IF(S19>100%,"false","good") -> good
A20: TXN019 | B20: 2026-01-13 | C20: em06 | D20: PR03 | E20: Sipho Dlamini | F20: 2 | G20: 1800 | H20: 3600 | I20: COMPLETED | J20: =_xlfn.XLOOKUP(C20,'STAFF TABLE'!A5:A14,'STAFF TABLE'!B5:B14) -> Lebo Mahlangu | K20: =_xlfn.XLOOKUP(C20,'STAFF TABLE'!$A$2:$A$11,'STAFF TABLE'!$C$2:$C$11) -> Polokwane Branch | L20: =_xlfn.XLOOKUP(C20,'STAFF TABLE'!$A$2:$A$11,'STAFF TABLE'!$D$2:$D$11) -> Limpopo | M20: =_xlfn.XLOOKUP(C20,'STAFF TABLE'!$A$2:$A$11,'STAFF TABLE'!$E$2:$E$11) -> 0.07 | N20: =_xlfn.XLOOKUP(D20,'PRODUCT CATALOGUE'!$A$2:$A$13,'PRODUCT CATALOGUE'!$B$2:$B$13) -> Wireless Headset | O20: =_xlfn.XLOOKUP(D20,'PRODUCT CATALOGUE'!$A$2:$A$13,'PRODUCT CATALOGUE'!$C$2:$C$13) -> Electronics | P20: =_xlfn.XLOOKUP(D20,'PRODUCT CATALOGUE'!$A$2:$A$13,'PRODUCT CATALOGUE'!$E$2:$E$13) -> 950 | Q20: 3600 | R20: =Q20-P20 -> 2650 | S20: =R20/Q20 -> 0.73611111 | T20: =M20*Q20 -> 252 | U20: =IF(S20>100%,"false","good") -> good
A21: TXN020 | B21: 2026-01-14 | C21: EM10 | D21: PR09 | E21: David Moyo | F21: 3 | G21: 4800 | H21: 14400 | I21: COMPLETED | J21: =_xlfn.XLOOKUP(C21,'STAFF TABLE'!A11:A20,'STAFF TABLE'!B11:B20) -> Sipho Dlamini | K21: =_xlfn.XLOOKUP(C21,'STAFF TABLE'!$A$2:$A$11,'STAFF TABLE'!$C$2:$C$11) -> Durban Branch | L21: =_xlfn.XLOOKUP(C21,'STAFF TABLE'!$A$2:$A$11,'STAFF TABLE'!$D$2:$D$11) -> KZN | M21: =_xlfn.XLOOKUP(C21,'STAFF TABLE'!$A$2:$A$11,'STAFF TABLE'!$E$2:$E$11) -> 0.1 | N21: =_xlfn.XLOOKUP(D21,'PRODUCT CATALOGUE'!$A$2:$A$13,'PRODUCT CATALOGUE'!$B$2:$B$13) -> Monitor 27inch | O21: =_xlfn.XLOOKUP(D21,'PRODUCT CATALOGUE'!$A$2:$A$13,'PRODUCT CATALOGUE'!$C$2:$C$13) -> Electronics | P21: =_xlfn.XLOOKUP(D21,'PRODUCT CATALOGUE'!$A$2:$A$13,'PRODUCT CATALOGUE'!$E$2:$E$13) -> 2900 | Q21: 14400 | R21: =Q21-P21 -> 11500 | S21: =R21/Q21 -> 0.79861111 | T21: =M21*Q21 -> 1440 | U21: =IF(S21>100%,"false","good") -> good
A22: TXN021 | B22: 2026-01-15 | C22: EM07 | D22: PR02 | E22: Priya Pillay | F22: 2 | G22: 3200 | H22: 6400 | I22: PENDING | J22: =_xlfn.XLOOKUP(C22,'STAFF TABLE'!A2:A11,'STAFF TABLE'!B2:B11) -> Fatima Patel | K22: =_xlfn.XLOOKUP(C22,'STAFF TABLE'!$A$2:$A$11,'STAFF TABLE'!$C$2:$C$11) -> Cape Town Branch | L22: =_xlfn.XLOOKUP(C22,'STAFF TABLE'!$A$2:$A$11,'STAFF TABLE'!$D$2:$D$11) -> Western Cape | M22: =_xlfn.XLOOKUP(C22,'STAFF TABLE'!$A$2:$A$11,'STAFF TABLE'!$E$2:$E$11) -> 0.09 | N22: =_xlfn.XLOOKUP(D22,'PRODUCT CATALOGUE'!$A$2:$A$13,'PRODUCT CATALOGUE'!$B$2:$B$13) -> Office Chair | O22: =_xlfn.XLOOKUP(D22,'PRODUCT CATALOGUE'!$A$2:$A$13,'PRODUCT CATALOGUE'!$C$2:$C$13) -> Furniture | P22: =_xlfn.XLOOKUP(D22,'PRODUCT CATALOGUE'!$A$2:$A$13,'PRODUCT CATALOGUE'!$E$2:$E$13) -> 1750 | Q22: 6400 | R22: =Q22-P22 -> 4650 | S22: =R22/Q22 -> 0.7265625 | T22: =M22*Q22 -> 576 | U22: =IF(S22>100%,"false","good") -> good
A23: TXN022 | B23: 15/01/2026 | C23: EM03 | D23: PR10 | E23: Zanele Mokoena | F23: 6 | G23: 650 | H23: 3900 | I23: COMPLETED | J23: =_xlfn.XLOOKUP(C23,'STAFF TABLE'!A3:A12,'STAFF TABLE'!B3:B12) -> Zanele Dlamini | K23: =_xlfn.XLOOKUP(C23,'STAFF TABLE'!$A$2:$A$11,'STAFF TABLE'!$C$2:$C$11) -> Cape Town Branch | L23: =_xlfn.XLOOKUP(C23,'STAFF TABLE'!$A$2:$A$11,'STAFF TABLE'!$D$2:$D$11) -> Western Cape | M23: =_xlfn.XLOOKUP(C23,'STAFF TABLE'!$A$2:$A$11,'STAFF TABLE'!$E$2:$E$11) -> 0.09 | N23: =_xlfn.XLOOKUP(D23,'PRODUCT CATALOGUE'!$A$2:$A$13,'PRODUCT CATALOGUE'!$B$2:$B$13) -> Ergonomic Mouse | O23: =_xlfn.XLOOKUP(D23,'PRODUCT CATALOGUE'!$A$2:$A$13,'PRODUCT CATALOGUE'!$C$2:$C$13) -> Electronics | P23: =_xlfn.XLOOKUP(D23,'PRODUCT CATALOGUE'!$A$2:$A$13,'PRODUCT CATALOGUE'!$E$2:$E$13) -> 310 | Q23: 3900 | R23: =Q23-P23 -> 3590 | S23: =R23/Q23 -> 0.92051282 | T23: =M23*Q23 -> 351 | U23: =IF(S23>100%,"false","good") -> good
A24: TXN023 | B24: 2026-01-16 | C24: EM05 | D24: PR11 | E24: Riaan Botha | F24: 1 | G24: 2800 | H24: 2800 | I24: COMPLETED | J24: =_xlfn.XLOOKUP(C24,'STAFF TABLE'!A4:A13,'STAFF TABLE'!B4:B13) -> Amahle Zulu | K24: =_xlfn.XLOOKUP(C24,'STAFF TABLE'!$A$2:$A$11,'STAFF TABLE'!$C$2:$C$11) -> Durban Branch | L24: =_xlfn.XLOOKUP(C24,'STAFF TABLE'!$A$2:$A$11,'STAFF TABLE'!$D$2:$D$11) -> KZN | M24: =_xlfn.XLOOKUP(C24,'STAFF TABLE'!$A$2:$A$11,'STAFF TABLE'!$E$2:$E$11) -> 0.1 | N24: =_xlfn.XLOOKUP(D24,'PRODUCT CATALOGUE'!$A$2:$A$13,'PRODUCT CATALOGUE'!$B$2:$B$13) -> Filing Cabinet | O24: =_xlfn.XLOOKUP(D24,'PRODUCT CATALOGUE'!$A$2:$A$13,'PRODUCT CATALOGUE'!$C$2:$C$13) -> Furniture | P24: =_xlfn.XLOOKUP(D24,'PRODUCT CATALOGUE'!$A$2:$A$13,'PRODUCT CATALOGUE'!$E$2:$E$13) -> 1600 | Q24: 2800 | R24: =Q24-P24 -> 1200 | S24: =R24/Q24 -> 0.42857143 | T24: =M24*Q24 -> 280 | U24: =IF(S24>100%,"false","good") -> good
A25: TXN024 | B25: 2026-01-16 | C25: EM08 | D25: PR01 | E25: Amahle Zulu | F25: 2 | G25: 15000 | H25: 28000 | I25: COMPLETED | J25: =_xlfn.XLOOKUP(C25,'STAFF TABLE'!A5:A14,'STAFF TABLE'!B5:B14) -> Kefilwe Sithole | K25: =_xlfn.XLOOKUP(C25,'STAFF TABLE'!$A$2:$A$11,'STAFF TABLE'!$C$2:$C$11) -> Sandton Branch | L25: =_xlfn.XLOOKUP(C25,'STAFF TABLE'!$A$2:$A$11,'STAFF TABLE'!$D$2:$D$11) -> Gauteng | M25: =_xlfn.XLOOKUP(C25,'STAFF TABLE'!$A$2:$A$11,'STAFF TABLE'!$E$2:$E$11) -> 0.08 | N25: =_xlfn.XLOOKUP(D25,'PRODUCT CATALOGUE'!$A$2:$A$13,'PRODUCT CATALOGUE'!$B$2:$B$13) -> Gaming Laptop | O25: =_xlfn.XLOOKUP(D25,'PRODUCT CATALOGUE'!$A$2:$A$13,'PRODUCT CATALOGUE'!$C$2:$C$13) -> Electronics | P25: =_xlfn.XLOOKUP(D25,'PRODUCT CATALOGUE'!$A$2:$A$13,'PRODUCT CATALOGUE'!$E$2:$E$13) -> 9800 | Q25: 30000 | R25: =Q25-P25 -> 20200 | S25: =R25/Q25 -> 0.67333333 | T25: =M25*Q25 -> 2400 | U25: =IF(S25>100%,"false","good") -> good
A26: TXN025 | B26: 2026-01-17 | C26: EM02 | D26: PR08 | E26: Lebo Mahlangu | F26: 4 | G26: 890 | H26: 3560 | I26: COMPLETED | J26: =_xlfn.XLOOKUP(C26,'STAFF TABLE'!$A$2:$A$11,'STAFF TABLE'!$B$2:$B$11) -> Priya Pillay | K26: =_xlfn.XLOOKUP(C26,'STAFF TABLE'!$A$2:$A$11,'STAFF TABLE'!$C$2:$C$11) -> Durban Branch | L26: =_xlfn.XLOOKUP(C26,'STAFF TABLE'!$A$2:$A$11,'STAFF TABLE'!$D$2:$D$11) -> KZN | M26: =_xlfn.XLOOKUP(C26,'STAFF TABLE'!$A$2:$A$11,'STAFF TABLE'!$E$2:$E$11) -> 0.1 | N26: =_xlfn.XLOOKUP(D26,'PRODUCT CATALOGUE'!$A$2:$A$13,'PRODUCT CATALOGUE'!$B$2:$B$13) -> Whiteboard | O26: =_xlfn.XLOOKUP(D26,'PRODUCT CATALOGUE'!$A$2:$A$13,'PRODUCT CATALOGUE'!$C$2:$C$13) -> Stationery | P26: =_xlfn.XLOOKUP(D26,'PRODUCT CATALOGUE'!$A$2:$A$13,'PRODUCT CATALOGUE'!$E$2:$E$13) -> 420 | Q26: 3560 | R26: =Q26-P26 -> 3140 | S26: =R26/Q26 -> 0.88202247 | T26: =M26*Q26 -> 356 | U26: =IF(S26>100%,"false","good") -> good
A27: TXN026 | B27: 2026-01-19 | C27: EM09 | D27: PR06 | E27: Fatima Patel | F27: 20 | G27: 350 | H27: 7000 | I27: COMPLETED | J27: =_xlfn.XLOOKUP(C27,'STAFF TABLE'!$A$2:$A$11,'STAFF TABLE'!$B$2:$B$11) -> David Moyo | K27: =_xlfn.XLOOKUP(C27,'STAFF TABLE'!$A$2:$A$11,'STAFF TABLE'!$C$2:$C$11) -> Polokwane Branch | L27: =_xlfn.XLOOKUP(C27,'STAFF TABLE'!$A$2:$A$11,'STAFF TABLE'!$D$2:$D$11) -> Limpopo | M27: =_xlfn.XLOOKUP(C27,'STAFF TABLE'!$A$2:$A$11,'STAFF TABLE'!$E$2:$E$11) -> 0.07 | N27: =_xlfn.XLOOKUP(D27,'PRODUCT CATALOGUE'!$A$2:$A$13,'PRODUCT CATALOGUE'!$B$2:$B$13) -> Notebook Bundle | O27: =_xlfn.XLOOKUP(D27,'PRODUCT CATALOGUE'!$A$2:$A$13,'PRODUCT CATALOGUE'!$C$2:$C$13) -> Stationery | P27: =_xlfn.XLOOKUP(D27,'PRODUCT CATALOGUE'!$A$2:$A$13,'PRODUCT CATALOGUE'!$E$2:$E$13) -> 140 | Q27: 7000 | R27: =Q27-P27 -> 6860 | S27: =R27/Q27 -> 0.98 | T27: =M27*Q27 -> 490 | U27: =IF(S27>100%,"false","good") -> good
A28: TXN027 | B28: 19/01/2026 | C28: EM01 | D28: PR05 | E28: Nomsa Khumalo | F28: 2 | G28: 1200 | H28: 2400 | I28: COMPLETED | J28: =_xlfn.XLOOKUP(C28,'STAFF TABLE'!$A$2:$A$11,'STAFF TABLE'!$B$2:$B$11) -> Thabo Nkosi | K28: =_xlfn.XLOOKUP(C28,'STAFF TABLE'!$A$2:$A$11,'STAFF TABLE'!$C$2:$C$11) -> Sandton Branch | L28: =_xlfn.XLOOKUP(C28,'STAFF TABLE'!$A$2:$A$11,'STAFF TABLE'!$D$2:$D$11) -> Gauteng | M28: =_xlfn.XLOOKUP(C28,'STAFF TABLE'!$A$2:$A$11,'STAFF TABLE'!$E$2:$E$11) -> 0.08 | N28: =_xlfn.XLOOKUP(D28,'PRODUCT CATALOGUE'!$A$2:$A$13,'PRODUCT CATALOGUE'!$B$2:$B$13) -> Webcam HD | O28: =_xlfn.XLOOKUP(D28,'PRODUCT CATALOGUE'!$A$2:$A$13,'PRODUCT CATALOGUE'!$C$2:$C$13) -> Electronics | P28: =_xlfn.XLOOKUP(D28,'PRODUCT CATALOGUE'!$A$2:$A$13,'PRODUCT CATALOGUE'!$E$2:$E$13) -> 620 | Q28: 2400 | R28: =Q28-P28 -> 1780 | S28: =R28/Q28 -> 0.74166667 | T28: =M28*Q28 -> 192 | U28: =IF(S28>100%,"false","good") -> good
A29: TXN028 | B29: 2026-01-20 | C29: EM04 | D29: PR09 | E29: Pieter van Wyk | F29: 1 | G29: 4800 | H29: N/A | I29: COMPLETED | J29: =_xlfn.XLOOKUP(C29,'STAFF TABLE'!$A$2:$A$11,'STAFF TABLE'!$B$2:$B$11) -> Riaan Botha | K29: =_xlfn.XLOOKUP(C29,'STAFF TABLE'!$A$2:$A$11,'STAFF TABLE'!$C$2:$C$11) -> Sandton Branch | L29: =_xlfn.XLOOKUP(C29,'STAFF TABLE'!$A$2:$A$11,'STAFF TABLE'!$D$2:$D$11) -> Gauteng | M29: =_xlfn.XLOOKUP(C29,'STAFF TABLE'!$A$2:$A$11,'STAFF TABLE'!$E$2:$E$11) -> 0.08 | N29: =_xlfn.XLOOKUP(D29,'PRODUCT CATALOGUE'!$A$2:$A$13,'PRODUCT CATALOGUE'!$B$2:$B$13) -> Monitor 27inch | O29: =_xlfn.XLOOKUP(D29,'PRODUCT CATALOGUE'!$A$2:$A$13,'PRODUCT CATALOGUE'!$C$2:$C$13) -> Electronics | P29: =_xlfn.XLOOKUP(D29,'PRODUCT CATALOGUE'!$A$2:$A$13,'PRODUCT CATALOGUE'!$E$2:$E$13) -> 2900 | Q29: 4800 | R29: =Q29-P29 -> 1900 | S29: =R29/Q29 -> 0.39583333 | T29: =M29*Q29 -> 384 | U29: =IF(S29>100%,"false","good") -> good
A30: TXN029 | B30: 2026-01-20 | C30: EM07 | D30: PR12 | E30: Kefilwe Sithole | F30: 25 | G30: 120 | H30: 3000 | I30: COMPLETED | J30: =_xlfn.XLOOKUP(C30,'STAFF TABLE'!$A$2:$A$11,'STAFF TABLE'!$B$2:$B$11) -> Fatima Patel | K30: =_xlfn.XLOOKUP(C30,'STAFF TABLE'!$A$2:$A$11,'STAFF TABLE'!$C$2:$C$11) -> Cape Town Branch | L30: =_xlfn.XLOOKUP(C30,'STAFF TABLE'!$A$2:$A$11,'STAFF TABLE'!$D$2:$D$11) -> Western Cape | M30: =_xlfn.XLOOKUP(C30,'STAFF TABLE'!$A$2:$A$11,'STAFF TABLE'!$E$2:$E$11) -> 0.09 | N30: =_xlfn.XLOOKUP(D30,'PRODUCT CATALOGUE'!$A$2:$A$13,'PRODUCT CATALOGUE'!$B$2:$B$13) -> Printer Paper Ream | O30: =_xlfn.XLOOKUP(D30,'PRODUCT CATALOGUE'!$A$2:$A$13,'PRODUCT CATALOGUE'!$C$2:$C$13) -> Stationery | P30: =_xlfn.XLOOKUP(D30,'PRODUCT CATALOGUE'!$A$2:$A$13,'PRODUCT CATALOGUE'!$E$2:$E$13) -> 55 | Q30: 3000 | R30: =Q30-P30 -> 2945 | S30: =R30/Q30 -> 0.98166667 | T30: =M30*Q30 -> 270 | U30: =IF(S30>100%,"false","good") -> good
A31: TXN030 | B31: 2026-01-21 | C31: EM10 | D31: PR07 | E31: Sipho Dlamini | F31: 2 | G31: 2100 | H31: 4200 | I31: COMPLETED | J31: =_xlfn.XLOOKUP(C31,'STAFF TABLE'!$A$2:$A$11,'STAFF TABLE'!$B$2:$B$11) -> Sipho Dlamini | K31: =_xlfn.XLOOKUP(C31,'STAFF TABLE'!$A$2:$A$11,'STAFF TABLE'!$C$2:$C$11) -> Durban Branch | L31: =_xlfn.XLOOKUP(C31,'STAFF TABLE'!$A$2:$A$11,'STAFF TABLE'!$D$2:$D$11) -> KZN | M31: =_xlfn.XLOOKUP(C31,'STAFF TABLE'!$A$2:$A$11,'STAFF TABLE'!$E$2:$E$11) -> 0.1 | N31: =_xlfn.XLOOKUP(D31,'PRODUCT CATALOGUE'!$A$2:$A$13,'PRODUCT CATALOGUE'!$B$2:$B$13) -> Mechanical Keyboard | O31: =_xlfn.XLOOKUP(D31,'PRODUCT CATALOGUE'!$A$2:$A$13,'PRODUCT CATALOGUE'!$C$2:$C$13) -> Electronics | P31: =_xlfn.XLOOKUP(D31,'PRODUCT CATALOGUE'!$A$2:$A$13,'PRODUCT CATALOGUE'!$E$2:$E$13) -> 1100 | Q31: 4200 | R31: =Q31-P31 -> 3100 | S31: =R31/Q31 -> 0.73809524 | T31: =M31*Q31 -> 420 | U31: =IF(S31>100%,"false","good") -> good
A32: TXN031 | B32: 2026-02-03 | C32: EM03 | D32: PR01 | E32: David Moyo | F32: 1 | G32: 15000 | H32: 15000 | I32: COMPLETED | J32: =_xlfn.XLOOKUP(C32,'STAFF TABLE'!$A$2:$A$11,'STAFF TABLE'!$B$2:$B$11) -> Zanele Dlamini | K32: =_xlfn.XLOOKUP(C32,'STAFF TABLE'!$A$2:$A$11,'STAFF TABLE'!$C$2:$C$11) -> Cape Town Branch | L32: =_xlfn.XLOOKUP(C32,'STAFF TABLE'!$A$2:$A$11,'STAFF TABLE'!$D$2:$D$11) -> Western Cape | M32: =_xlfn.XLOOKUP(C32,'STAFF TABLE'!$A$2:$A$11,'STAFF TABLE'!$E$2:$E$11) -> 0.09 | N32: =_xlfn.XLOOKUP(D32,'PRODUCT CATALOGUE'!$A$2:$A$13,'PRODUCT CATALOGUE'!$B$2:$B$13) -> Gaming Laptop | O32: =_xlfn.XLOOKUP(D32,'PRODUCT CATALOGUE'!$A$2:$A$13,'PRODUCT CATALOGUE'!$C$2:$C$13) -> Electronics | P32: =_xlfn.XLOOKUP(D32,'PRODUCT CATALOGUE'!$A$2:$A$13,'PRODUCT CATALOGUE'!$E$2:$E$13) -> 9800 | Q32: 15000 | R32: =Q32-P32 -> 5200 | S32: =R32/Q32 -> 0.34666667 | T32: =M32*Q32 -> 1350 | U32: =IF(S32>100%,"false","good") -> good
A33: TXN032 | B33: 03/02/2026 | C33: EM06 | D33: PR04 | F33: 2 | G33: 5500 | H33: 11000 | I33: COMPLETED | J33: =_xlfn.XLOOKUP(C33,'STAFF TABLE'!$A$2:$A$11,'STAFF TABLE'!$B$2:$B$11) -> Lebo Mahlangu | K33: =_xlfn.XLOOKUP(C33,'STAFF TABLE'!$A$2:$A$11,'STAFF TABLE'!$C$2:$C$11) -> Polokwane Branch | L33: =_xlfn.XLOOKUP(C33,'STAFF TABLE'!$A$2:$A$11,'STAFF TABLE'!$D$2:$D$11) -> Limpopo | M33: =_xlfn.XLOOKUP(C33,'STAFF TABLE'!$A$2:$A$11,'STAFF TABLE'!$E$2:$E$11) -> 0.07 | N33: =_xlfn.XLOOKUP(D33,'PRODUCT CATALOGUE'!$A$2:$A$13,'PRODUCT CATALOGUE'!$B$2:$B$13) -> Standing Desk | O33: =_xlfn.XLOOKUP(D33,'PRODUCT CATALOGUE'!$A$2:$A$13,'PRODUCT CATALOGUE'!$C$2:$C$13) -> Furniture | P33: =_xlfn.XLOOKUP(D33,'PRODUCT CATALOGUE'!$A$2:$A$13,'PRODUCT CATALOGUE'!$E$2:$E$13) -> 3100 | Q33: 11000 | R33: =Q33-P33 -> 7900 | S33: =R33/Q33 -> 0.71818182 | T33: =M33*Q33 -> 770 | U33: =IF(S33>100%,"false","good") -> good
A34: TXN033 | B34: 2026-02-04 | C34: EM01 | D34: PR03 | E34: Priya Pillay | F34: 3 | G34: 1800 | H34: 5400 | I34: COMPLETED | J34: =_xlfn.XLOOKUP(C34,'STAFF TABLE'!$A$2:$A$11,'STAFF TABLE'!$B$2:$B$11) -> Thabo Nkosi | K34: =_xlfn.XLOOKUP(C34,'STAFF TABLE'!$A$2:$A$11,'STAFF TABLE'!$C$2:$C$11) -> Sandton Branch | L34: =_xlfn.XLOOKUP(C34,'STAFF TABLE'!$A$2:$A$11,'STAFF TABLE'!$D$2:$D$11) -> Gauteng | M34: =_xlfn.XLOOKUP(C34,'STAFF TABLE'!$A$2:$A$11,'STAFF TABLE'!$E$2:$E$11) -> 0.08 | N34: =_xlfn.XLOOKUP(D34,'PRODUCT CATALOGUE'!$A$2:$A$13,'PRODUCT CATALOGUE'!$B$2:$B$13) -> Wireless Headset | O34: =_xlfn.XLOOKUP(D34,'PRODUCT CATALOGUE'!$A$2:$A$13,'PRODUCT CATALOGUE'!$C$2:$C$13) -> Electronics | P34: =_xlfn.XLOOKUP(D34,'PRODUCT CATALOGUE'!$A$2:$A$13,'PRODUCT CATALOGUE'!$E$2:$E$13) -> 950 | Q34: 5400 | R34: =Q34-P34 -> 4450 | S34: =R34/Q34 -> 0.82407407 | T34: =M34*Q34 -> 432 | U34: =IF(S34>100%,"false","good") -> good
A35: TXN034 | B35: 2026-02-04 | C35: EM05 | D35: PR08 | E35: Zanele Mokoena | F35: 5 | G35: 890 | H35: 4450 | I35: COMPLETED | J35: =_xlfn.XLOOKUP(C35,'STAFF TABLE'!$A$2:$A$11,'STAFF TABLE'!$B$2:$B$11) -> Amahle Zulu | K35: =_xlfn.XLOOKUP(C35,'STAFF TABLE'!$A$2:$A$11,'STAFF TABLE'!$C$2:$C$11) -> Durban Branch | L35: =_xlfn.XLOOKUP(C35,'STAFF TABLE'!$A$2:$A$11,'STAFF TABLE'!$D$2:$D$11) -> KZN | M35: =_xlfn.XLOOKUP(C35,'STAFF TABLE'!$A$2:$A$11,'STAFF TABLE'!$E$2:$E$11) -> 0.1 | N35: =_xlfn.XLOOKUP(D35,'PRODUCT CATALOGUE'!$A$2:$A$13,'PRODUCT CATALOGUE'!$B$2:$B$13) -> Whiteboard | O35: =_xlfn.XLOOKUP(D35,'PRODUCT CATALOGUE'!$A$2:$A$13,'PRODUCT CATALOGUE'!$C$2:$C$13) -> Stationery | P35: =_xlfn.XLOOKUP(D35,'PRODUCT CATALOGUE'!$A$2:$A$13,'PRODUCT CATALOGUE'!$E$2:$E$13) -> 420 | Q35: 4450 | R35: =Q35-P35 -> 4030 | S35: =R35/Q35 -> 0.90561798 | T35: =M35*Q35 -> 445 | U35: =IF(S35>100%,"false","good") -> good
A36: TXN035 | B36: 2026-02-05 | C36: EM08 | D36: PR09 | E36: Riaan Botha | F36: 2 | G36: 4800 | H36: 9600 | I36: COMPLETED | J36: =_xlfn.XLOOKUP(C36,'STAFF TABLE'!$A$2:$A$11,'STAFF TABLE'!$B$2:$B$11) -> Kefilwe Sithole | K36: =_xlfn.XLOOKUP(C36,'STAFF TABLE'!$A$2:$A$11,'STAFF TABLE'!$C$2:$C$11) -> Sandton Branch | L36: =_xlfn.XLOOKUP(C36,'STAFF TABLE'!$A$2:$A$11,'STAFF TABLE'!$D$2:$D$11) -> Gauteng | M36: =_xlfn.XLOOKUP(C36,'STAFF TABLE'!$A$2:$A$11,'STAFF TABLE'!$E$2:$E$11) -> 0.08 | N36: =_xlfn.XLOOKUP(D36,'PRODUCT CATALOGUE'!$A$2:$A$13,'PRODUCT CATALOGUE'!$B$2:$B$13) -> Monitor 27inch | O36: =_xlfn.XLOOKUP(D36,'PRODUCT CATALOGUE'!$A$2:$A$13,'PRODUCT CATALOGUE'!$C$2:$C$13) -> Electronics | P36: =_xlfn.XLOOKUP(D36,'PRODUCT CATALOGUE'!$A$2:$A$13,'PRODUCT CATALOGUE'!$E$2:$E$13) -> 2900 | Q36: 9600 | R36: =Q36-P36 -> 6700 | S36: =R36/Q36 -> 0.69791667 | T36: =M36*Q36 -> 768 | U36: =IF(S36>100%,"false","good") -> good
A37: TXN036 | B37: 2026-02-05 | C37: EM02 | D37: PR06 | E37: Amahle Zulu | F37: 12 | G37: 350 | H37: 4200 | I37: COMPLETED | J37: =_xlfn.XLOOKUP(C37,'STAFF TABLE'!$A$2:$A$11,'STAFF TABLE'!$B$2:$B$11) -> Priya Pillay | K37: =_xlfn.XLOOKUP(C37,'STAFF TABLE'!$A$2:$A$11,'STAFF TABLE'!$C$2:$C$11) -> Durban Branch | L37: =_xlfn.XLOOKUP(C37,'STAFF TABLE'!$A$2:$A$11,'STAFF TABLE'!$D$2:$D$11) -> KZN | M37: =_xlfn.XLOOKUP(C37,'STAFF TABLE'!$A$2:$A$11,'STAFF TABLE'!$E$2:$E$11) -> 0.1 | N37: =_xlfn.XLOOKUP(D37,'PRODUCT CATALOGUE'!$A$2:$A$13,'PRODUCT CATALOGUE'!$B$2:$B$13) -> Notebook Bundle | O37: =_xlfn.XLOOKUP(D37,'PRODUCT CATALOGUE'!$A$2:$A$13,'PRODUCT CATALOGUE'!$C$2:$C$13) -> Stationery | P37: =_xlfn.XLOOKUP(D37,'PRODUCT CATALOGUE'!$A$2:$A$13,'PRODUCT CATALOGUE'!$E$2:$E$13) -> 140 | Q37: 4200 | R37: =Q37-P37 -> 4060 | S37: =R37/Q37 -> 0.96666667 | T37: =M37*Q37 -> 420 | U37: =IF(S37>100%,"false","good") -> good
A38: TXN037 | B38: 05/02/2026 | C38: EM09 | D38: PR01 | E38: Lebo Mahlangu | F38: 1 | G38: 15000 | H38: 15000 | I38: COMPLETED | J38: =_xlfn.XLOOKUP(C38,'STAFF TABLE'!$A$2:$A$11,'STAFF TABLE'!$B$2:$B$11) -> David Moyo | K38: =_xlfn.XLOOKUP(C38,'STAFF TABLE'!$A$2:$A$11,'STAFF TABLE'!$C$2:$C$11) -> Polokwane Branch | L38: =_xlfn.XLOOKUP(C38,'STAFF TABLE'!$A$2:$A$11,'STAFF TABLE'!$D$2:$D$11) -> Limpopo | M38: =_xlfn.XLOOKUP(C38,'STAFF TABLE'!$A$2:$A$11,'STAFF TABLE'!$E$2:$E$11) -> 0.07 | N38: =_xlfn.XLOOKUP(D38,'PRODUCT CATALOGUE'!$A$2:$A$13,'PRODUCT CATALOGUE'!$B$2:$B$13) -> Gaming Laptop | O38: =_xlfn.XLOOKUP(D38,'PRODUCT CATALOGUE'!$A$2:$A$13,'PRODUCT CATALOGUE'!$C$2:$C$13) -> Electronics | P38: =_xlfn.XLOOKUP(D38,'PRODUCT CATALOGUE'!$A$2:$A$13,'PRODUCT CATALOGUE'!$E$2:$E$13) -> 9800 | Q38: 15000 | R38: =Q38-P38 -> 5200 | S38: =R38/Q38 -> 0.34666667 | T38: =M38*Q38 -> 1050 | U38: =IF(S38>100%,"false","good") -> good
A39: TXN038 | B39: 2026-02-06 | C39: EM07 | D39: PR11 | E39: Fatima Patel | F39: 3 | G39: 2800 | H39: 8400 | I39: COMPLETED | J39: =_xlfn.XLOOKUP(C39,'STAFF TABLE'!$A$2:$A$11,'STAFF TABLE'!$B$2:$B$11) -> Fatima Patel | K39: =_xlfn.XLOOKUP(C39,'STAFF TABLE'!$A$2:$A$11,'STAFF TABLE'!$C$2:$C$11) -> Cape Town Branch | L39: =_xlfn.XLOOKUP(C39,'STAFF TABLE'!$A$2:$A$11,'STAFF TABLE'!$D$2:$D$11) -> Western Cape | M39: =_xlfn.XLOOKUP(C39,'STAFF TABLE'!$A$2:$A$11,'STAFF TABLE'!$E$2:$E$11) -> 0.09 | N39: =_xlfn.XLOOKUP(D39,'PRODUCT CATALOGUE'!$A$2:$A$13,'PRODUCT CATALOGUE'!$B$2:$B$13) -> Filing Cabinet | O39: =_xlfn.XLOOKUP(D39,'PRODUCT CATALOGUE'!$A$2:$A$13,'PRODUCT CATALOGUE'!$C$2:$C$13) -> Furniture | P39: =_xlfn.XLOOKUP(D39,'PRODUCT CATALOGUE'!$A$2:$A$13,'PRODUCT CATALOGUE'!$E$2:$E$13) -> 1600 | Q39: 8400 | R39: =Q39-P39 -> 6800 | S39: =R39/Q39 -> 0.80952381 | T39: =M39*Q39 -> 756 | U39: =IF(S39>100%,"false","good") -> good
A40: TXN039 | B40: 2026-02-07 | C40: EM04 | D40: PR05 | E40: Nomsa Khumalo | F40: 4 | G40: 1200 | H40: 4800 | I40: COMPLETED | J40: =_xlfn.XLOOKUP(C40,'STAFF TABLE'!$A$2:$A$11,'STAFF TABLE'!$B$2:$B$11) -> Riaan Botha | K40: =_xlfn.XLOOKUP(C40,'STAFF TABLE'!$A$2:$A$11,'STAFF TABLE'!$C$2:$C$11) -> Sandton Branch | L40: =_xlfn.XLOOKUP(C40,'STAFF TABLE'!$A$2:$A$11,'STAFF TABLE'!$D$2:$D$11) -> Gauteng | M40: =_xlfn.XLOOKUP(C40,'STAFF TABLE'!$A$2:$A$11,'STAFF TABLE'!$E$2:$E$11) -> 0.08 | N40: =_xlfn.XLOOKUP(D40,'PRODUCT CATALOGUE'!$A$2:$A$13,'PRODUCT CATALOGUE'!$B$2:$B$13) -> Webcam HD | O40: =_xlfn.XLOOKUP(D40,'PRODUCT CATALOGUE'!$A$2:$A$13,'PRODUCT CATALOGUE'!$C$2:$C$13) -> Electronics | P40: =_xlfn.XLOOKUP(D40,'PRODUCT CATALOGUE'!$A$2:$A$13,'PRODUCT CATALOGUE'!$E$2:$E$13) -> 620 | Q40: 4800 | R40: =Q40-P40 -> 4180 | S40: =R40/Q40 -> 0.87083333 | T40: =M40*Q40 -> 384 | U40: =IF(S40>100%,"false","good") -> good
A41: TXN040 | B41: 2026-02-07 | C41: EM10 | D41: PR02 | E41: Pieter van Wyk | F41: 1 | G41: 3200 | H41: 3200 | I41: PENDING | J41: =_xlfn.XLOOKUP(C41,'STAFF TABLE'!$A$2:$A$11,'STAFF TABLE'!$B$2:$B$11) -> Sipho Dlamini | K41: =_xlfn.XLOOKUP(C41,'STAFF TABLE'!$A$2:$A$11,'STAFF TABLE'!$C$2:$C$11) -> Durban Branch | L41: =_xlfn.XLOOKUP(C41,'STAFF TABLE'!$A$2:$A$11,'STAFF TABLE'!$D$2:$D$11) -> KZN | M41: =_xlfn.XLOOKUP(C41,'STAFF TABLE'!$A$2:$A$11,'STAFF TABLE'!$E$2:$E$11) -> 0.1 | N41: =_xlfn.XLOOKUP(D41,'PRODUCT CATALOGUE'!$A$2:$A$13,'PRODUCT CATALOGUE'!$B$2:$B$13) -> Office Chair | O41: =_xlfn.XLOOKUP(D41,'PRODUCT CATALOGUE'!$A$2:$A$13,'PRODUCT CATALOGUE'!$C$2:$C$13) -> Furniture | P41: =_xlfn.XLOOKUP(D41,'PRODUCT CATALOGUE'!$A$2:$A$13,'PRODUCT CATALOGUE'!$E$2:$E$13) -> 1750 | Q41: 3200 | R41: =Q41-P41 -> 1450 | S41: =R41/Q41 -> 0.453125 | T41: =M41*Q41 -> 320 | U41: =IF(S41>100%,"false","good") -> good
A42: TXN041 | B42: 2026-02-10 | C42: EM03 | D42: PR10 | F42: 4 | G42: 650 | H42: 2600 | I42: COMPLETED | J42: =_xlfn.XLOOKUP(C42,'STAFF TABLE'!$A$2:$A$11,'STAFF TABLE'!$B$2:$B$11) -> Zanele Dlamini | K42: =_xlfn.XLOOKUP(C42,'STAFF TABLE'!$A$2:$A$11,'STAFF TABLE'!$C$2:$C$11) -> Cape Town Branch | L42: =_xlfn.XLOOKUP(C42,'STAFF TABLE'!$A$2:$A$11,'STAFF TABLE'!$D$2:$D$11) -> Western Cape | M42: =_xlfn.XLOOKUP(C42,'STAFF TABLE'!$A$2:$A$11,'STAFF TABLE'!$E$2:$E$11) -> 0.09 | N42: =_xlfn.XLOOKUP(D42,'PRODUCT CATALOGUE'!$A$2:$A$13,'PRODUCT CATALOGUE'!$B$2:$B$13) -> Ergonomic Mouse | O42: =_xlfn.XLOOKUP(D42,'PRODUCT CATALOGUE'!$A$2:$A$13,'PRODUCT CATALOGUE'!$C$2:$C$13) -> Electronics | P42: =_xlfn.XLOOKUP(D42,'PRODUCT CATALOGUE'!$A$2:$A$13,'PRODUCT CATALOGUE'!$E$2:$E$13) -> 310 | Q42: 2600 | R42: =Q42-P42 -> 2290 | S42: =R42/Q42 -> 0.88076923 | T42: =M42*Q42 -> 234 | U42: =IF(S42>100%,"false","good") -> good
A43: TXN042 | B43: 10/02/2026 | C43: EM01 | D43: PR07 | E43: Sipho Dlamini | F43: 3 | G43: 2100 | H43: 6300 | I43: COMPLETED | J43: =_xlfn.XLOOKUP(C43,'STAFF TABLE'!$A$2:$A$11,'STAFF TABLE'!$B$2:$B$11) -> Thabo Nkosi | K43: =_xlfn.XLOOKUP(C43,'STAFF TABLE'!$A$2:$A$11,'STAFF TABLE'!$C$2:$C$11) -> Sandton Branch | L43: =_xlfn.XLOOKUP(C43,'STAFF TABLE'!$A$2:$A$11,'STAFF TABLE'!$D$2:$D$11) -> Gauteng | M43: =_xlfn.XLOOKUP(C43,'STAFF TABLE'!$A$2:$A$11,'STAFF TABLE'!$E$2:$E$11) -> 0.08 | N43: =_xlfn.XLOOKUP(D43,'PRODUCT CATALOGUE'!$A$2:$A$13,'PRODUCT CATALOGUE'!$B$2:$B$13) -> Mechanical Keyboard | O43: =_xlfn.XLOOKUP(D43,'PRODUCT CATALOGUE'!$A$2:$A$13,'PRODUCT CATALOGUE'!$C$2:$C$13) -> Electronics | P43: =_xlfn.XLOOKUP(D43,'PRODUCT CATALOGUE'!$A$2:$A$13,'PRODUCT CATALOGUE'!$E$2:$E$13) -> 1100 | Q43: 6300 | R43: =Q43-P43 -> 5200 | S43: =R43/Q43 -> 0.82539683 | T43: =M43*Q43 -> 504 | U43: =IF(S43>100%,"false","good") -> good
A44: TXN043 | B44: 2026-02-11 | C44: EM06 | D44: PR12 | E44: David Moyo | F44: 30 | G44: 120 | H44: 3600 | I44: COMPLETED | J44: =_xlfn.XLOOKUP(C44,'STAFF TABLE'!$A$2:$A$11,'STAFF TABLE'!$B$2:$B$11) -> Lebo Mahlangu | K44: =_xlfn.XLOOKUP(C44,'STAFF TABLE'!$A$2:$A$11,'STAFF TABLE'!$C$2:$C$11) -> Polokwane Branch | L44: =_xlfn.XLOOKUP(C44,'STAFF TABLE'!$A$2:$A$11,'STAFF TABLE'!$D$2:$D$11) -> Limpopo | M44: =_xlfn.XLOOKUP(C44,'STAFF TABLE'!$A$2:$A$11,'STAFF TABLE'!$E$2:$E$11) -> 0.07 | N44: =_xlfn.XLOOKUP(D44,'PRODUCT CATALOGUE'!$A$2:$A$13,'PRODUCT CATALOGUE'!$B$2:$B$13) -> Printer Paper Ream | O44: =_xlfn.XLOOKUP(D44,'PRODUCT CATALOGUE'!$A$2:$A$13,'PRODUCT CATALOGUE'!$C$2:$C$13) -> Stationery | P44: =_xlfn.XLOOKUP(D44,'PRODUCT CATALOGUE'!$A$2:$A$13,'PRODUCT CATALOGUE'!$E$2:$E$13) -> 55 | Q44: 3600 | R44: =Q44-P44 -> 3545 | S44: =R44/Q44 -> 0.98472222 | T44: =M44*Q44 -> 252 | U44: =IF(S44>100%,"false","good") -> good
A45: TXN044 | B45: 2026-02-11 | C45: EM05 | D45: PR09 | E45: Priya Pillay | F45: 2 | G45: 4800 | H45: 9600 | I45: COMPLETED | J45: =_xlfn.XLOOKUP(C45,'STAFF TABLE'!$A$2:$A$11,'STAFF TABLE'!$B$2:$B$11) -> Amahle Zulu | K45: =_xlfn.XLOOKUP(C45,'STAFF TABLE'!$A$2:$A$11,'STAFF TABLE'!$C$2:$C$11) -> Durban Branch | L45: =_xlfn.XLOOKUP(C45,'STAFF TABLE'!$A$2:$A$11,'STAFF TABLE'!$D$2:$D$11) -> KZN | M45: =_xlfn.XLOOKUP(C45,'STAFF TABLE'!$A$2:$A$11,'STAFF TABLE'!$E$2:$E$11) -> 0.1 | N45: =_xlfn.XLOOKUP(D45,'PRODUCT CATALOGUE'!$A$2:$A$13,'PRODUCT CATALOGUE'!$B$2:$B$13) -> Monitor 27inch | O45: =_xlfn.XLOOKUP(D45,'PRODUCT CATALOGUE'!$A$2:$A$13,'PRODUCT CATALOGUE'!$C$2:$C$13) -> Electronics | P45: =_xlfn.XLOOKUP(D45,'PRODUCT CATALOGUE'!$A$2:$A$13,'PRODUCT CATALOGUE'!$E$2:$E$13) -> 2900 | Q45: 9600 | R45: =Q45-P45 -> 6700 | S45: =R45/Q45 -> 0.69791667 | T45: =M45*Q45 -> 960 | U45: =IF(S45>100%,"false","good") -> good
A46: TXN045 | B46: 2026-02-12 | C46: EM08 | D46: PR01 | E46: Zanele Mokoena | F46: 1 | G46: 15000 | H46: 14000 | I46: COMPLETED | J46: =_xlfn.XLOOKUP(C46,'STAFF TABLE'!$A$2:$A$11,'STAFF TABLE'!$B$2:$B$11) -> Kefilwe Sithole | K46: =_xlfn.XLOOKUP(C46,'STAFF TABLE'!$A$2:$A$11,'STAFF TABLE'!$C$2:$C$11) -> Sandton Branch | L46: =_xlfn.XLOOKUP(C46,'STAFF TABLE'!$A$2:$A$11,'STAFF TABLE'!$D$2:$D$11) -> Gauteng | M46: =_xlfn.XLOOKUP(C46,'STAFF TABLE'!$A$2:$A$11,'STAFF TABLE'!$E$2:$E$11) -> 0.08 | N46: =_xlfn.XLOOKUP(D46,'PRODUCT CATALOGUE'!$A$2:$A$13,'PRODUCT CATALOGUE'!$B$2:$B$13) -> Gaming Laptop | O46: =_xlfn.XLOOKUP(D46,'PRODUCT CATALOGUE'!$A$2:$A$13,'PRODUCT CATALOGUE'!$C$2:$C$13) -> Electronics | P46: =_xlfn.XLOOKUP(D46,'PRODUCT CATALOGUE'!$A$2:$A$13,'PRODUCT CATALOGUE'!$E$2:$E$13) -> 9800 | Q46: 15000 | R46: =Q46-P46 -> 5200 | S46: =R46/Q46 -> 0.34666667 | T46: =M46*Q46 -> 1200 | U46: =IF(S46>100%,"false","good") -> good
A47: TXN046 | B47: 2026-02-12 | C47: em08 | D47: PR04 | E47: Riaan Botha | F47: 1 | G47: 5500 | H47: 5500 | I47: COMPLETED | J47: =_xlfn.XLOOKUP(C47,'STAFF TABLE'!$A$2:$A$11,'STAFF TABLE'!$B$2:$B$11) -> Kefilwe Sithole | K47: =_xlfn.XLOOKUP(C47,'STAFF TABLE'!$A$2:$A$11,'STAFF TABLE'!$C$2:$C$11) -> Sandton Branch | L47: =_xlfn.XLOOKUP(C47,'STAFF TABLE'!$A$2:$A$11,'STAFF TABLE'!$D$2:$D$11) -> Gauteng | M47: =_xlfn.XLOOKUP(C47,'STAFF TABLE'!$A$2:$A$11,'STAFF TABLE'!$E$2:$E$11) -> 0.08 | N47: =_xlfn.XLOOKUP(D47,'PRODUCT CATALOGUE'!$A$2:$A$13,'PRODUCT CATALOGUE'!$B$2:$B$13) -> Standing Desk | O47: =_xlfn.XLOOKUP(D47,'PRODUCT CATALOGUE'!$A$2:$A$13,'PRODUCT CATALOGUE'!$C$2:$C$13) -> Furniture | P47: =_xlfn.XLOOKUP(D47,'PRODUCT CATALOGUE'!$A$2:$A$13,'PRODUCT CATALOGUE'!$E$2:$E$13) -> 3100 | Q47: 5500 | R47: =Q47-P47 -> 2400 | S47: =R47/Q47 -> 0.43636364 | T47: =M47*Q47 -> 440 | U47: =IF(S47>100%,"false","good") -> good
A48: TXN047 | B48: 12/02/2026 | C48: EM02 | D48: PR03 | E48: Amahle Zulu | F48: 2 | G48: 1800 | H48: 3600 | I48: COMPLETED | J48: =_xlfn.XLOOKUP(C48,'STAFF TABLE'!$A$2:$A$11,'STAFF TABLE'!$B$2:$B$11) -> Priya Pillay | K48: =_xlfn.XLOOKUP(C48,'STAFF TABLE'!$A$2:$A$11,'STAFF TABLE'!$C$2:$C$11) -> Durban Branch | L48: =_xlfn.XLOOKUP(C48,'STAFF TABLE'!$A$2:$A$11,'STAFF TABLE'!$D$2:$D$11) -> KZN | M48: =_xlfn.XLOOKUP(C48,'STAFF TABLE'!$A$2:$A$11,'STAFF TABLE'!$E$2:$E$11) -> 0.1 | N48: =_xlfn.XLOOKUP(D48,'PRODUCT CATALOGUE'!$A$2:$A$13,'PRODUCT CATALOGUE'!$B$2:$B$13) -> Wireless Headset | O48: =_xlfn.XLOOKUP(D48,'PRODUCT CATALOGUE'!$A$2:$A$13,'PRODUCT CATALOGUE'!$C$2:$C$13) -> Electronics | P48: =_xlfn.XLOOKUP(D48,'PRODUCT CATALOGUE'!$A$2:$A$13,'PRODUCT CATALOGUE'!$E$2:$E$13) -> 950 | Q48: 3600 | R48: =Q48-P48 -> 2650 | S48: =R48/Q48 -> 0.73611111 | T48: =M48*Q48 -> 360 | U48: =IF(S48>100%,"false","good") -> good
A49: TXN048 | B49: 2026-02-13 | C49: EM09 | D49: PR08 | E49: Lebo Mahlangu | F49: 3 | G49: 890 | H49: 2670 | I49: COMPLETED | J49: =_xlfn.XLOOKUP(C49,'STAFF TABLE'!$A$2:$A$11,'STAFF TABLE'!$B$2:$B$11) -> David Moyo | K49: =_xlfn.XLOOKUP(C49,'STAFF TABLE'!$A$2:$A$11,'STAFF TABLE'!$C$2:$C$11) -> Polokwane Branch | L49: =_xlfn.XLOOKUP(C49,'STAFF TABLE'!$A$2:$A$11,'STAFF TABLE'!$D$2:$D$11) -> Limpopo | M49: =_xlfn.XLOOKUP(C49,'STAFF TABLE'!$A$2:$A$11,'STAFF TABLE'!$E$2:$E$11) -> 0.07 | N49: =_xlfn.XLOOKUP(D49,'PRODUCT CATALOGUE'!$A$2:$A$13,'PRODUCT CATALOGUE'!$B$2:$B$13) -> Whiteboard | O49: =_xlfn.XLOOKUP(D49,'PRODUCT CATALOGUE'!$A$2:$A$13,'PRODUCT CATALOGUE'!$C$2:$C$13) -> Stationery | P49: =_xlfn.XLOOKUP(D49,'PRODUCT CATALOGUE'!$A$2:$A$13,'PRODUCT CATALOGUE'!$E$2:$E$13) -> 420 | Q49: 2670 | R49: =Q49-P49 -> 2250 | S49: =R49/Q49 -> 0.84269663 | T49: =M49*Q49 -> 186.9 | U49: =IF(S49>100%,"false","good") -> good
A50: TXN049 | B50: 2026-02-14 | C50: EM07 | D50: PR06 | E50: Fatima Patel | F50: 8 | G50: 350 | H50: 2800 | I50: COMPLETED | J50: =_xlfn.XLOOKUP(C50,'STAFF TABLE'!$A$2:$A$11,'STAFF TABLE'!$B$2:$B$11) -> Fatima Patel | K50: =_xlfn.XLOOKUP(C50,'STAFF TABLE'!$A$2:$A$11,'STAFF TABLE'!$C$2:$C$11) -> Cape Town Branch | L50: =_xlfn.XLOOKUP(C50,'STAFF TABLE'!$A$2:$A$11,'STAFF TABLE'!$D$2:$D$11) -> Western Cape | M50: =_xlfn.XLOOKUP(C50,'STAFF TABLE'!$A$2:$A$11,'STAFF TABLE'!$E$2:$E$11) -> 0.09 | N50: =_xlfn.XLOOKUP(D50,'PRODUCT CATALOGUE'!$A$2:$A$13,'PRODUCT CATALOGUE'!$B$2:$B$13) -> Notebook Bundle | O50: =_xlfn.XLOOKUP(D50,'PRODUCT CATALOGUE'!$A$2:$A$13,'PRODUCT CATALOGUE'!$C$2:$C$13) -> Stationery | P50: =_xlfn.XLOOKUP(D50,'PRODUCT CATALOGUE'!$A$2:$A$13,'PRODUCT CATALOGUE'!$E$2:$E$13) -> 140 | Q50: 2800 | R50: =Q50-P50 -> 2660 | S50: =R50/Q50 -> 0.95 | T50: =M50*Q50 -> 252 | U50: =IF(S50>100%,"false","good") -> good
A51: TXN050 | B51: 2026-02-17 | C51: EM04 | D51: PR09 | E51: Nomsa Khumalo | F51: 3 | G51: 4800 | H51: TBC | I51: COMPLETED | J51: =_xlfn.XLOOKUP(C51,'STAFF TABLE'!$A$2:$A$11,'STAFF TABLE'!$B$2:$B$11) -> Riaan Botha | K51: =_xlfn.XLOOKUP(C51,'STAFF TABLE'!$A$2:$A$11,'STAFF TABLE'!$C$2:$C$11) -> Sandton Branch | L51: =_xlfn.XLOOKUP(C51,'STAFF TABLE'!$A$2:$A$11,'STAFF TABLE'!$D$2:$D$11) -> Gauteng | M51: =_xlfn.XLOOKUP(C51,'STAFF TABLE'!$A$2:$A$11,'STAFF TABLE'!$E$2:$E$11) -> 0.08 | N51: =_xlfn.XLOOKUP(D51,'PRODUCT CATALOGUE'!$A$2:$A$13,'PRODUCT CATALOGUE'!$B$2:$B$13) -> Monitor 27inch | O51: =_xlfn.XLOOKUP(D51,'PRODUCT CATALOGUE'!$A$2:$A$13,'PRODUCT CATALOGUE'!$C$2:$C$13) -> Electronics | P51: =_xlfn.XLOOKUP(D51,'PRODUCT CATALOGUE'!$A$2:$A$13,'PRODUCT CATALOGUE'!$E$2:$E$13) -> 2900 | Q51: 14400 | R51: =Q51-P51 -> 11500 | S51: =R51/Q51 -> 0.79861111 | T51: =M51*Q51 -> 1152 | U51: =IF(S51>100%,"false","good") -> good
A52: TXN051 | B52: 2026-02-18 | C52: EM10 | D52: PR11 | E52: Pieter van Wyk | F52: 2 | G52: 2800 | H52: 5600 | I52: COMPLETED | J52: =_xlfn.XLOOKUP(C52,'STAFF TABLE'!$A$2:$A$11,'STAFF TABLE'!$B$2:$B$11) -> Sipho Dlamini | K52: =_xlfn.XLOOKUP(C52,'STAFF TABLE'!$A$2:$A$11,'STAFF TABLE'!$C$2:$C$11) -> Durban Branch | L52: =_xlfn.XLOOKUP(C52,'STAFF TABLE'!$A$2:$A$11,'STAFF TABLE'!$D$2:$D$11) -> KZN | M52: =_xlfn.XLOOKUP(C52,'STAFF TABLE'!$A$2:$A$11,'STAFF TABLE'!$E$2:$E$11) -> 0.1 | N52: =_xlfn.XLOOKUP(D52,'PRODUCT CATALOGUE'!$A$2:$A$13,'PRODUCT CATALOGUE'!$B$2:$B$13) -> Filing Cabinet | O52: =_xlfn.XLOOKUP(D52,'PRODUCT CATALOGUE'!$A$2:$A$13,'PRODUCT CATALOGUE'!$C$2:$C$13) -> Furniture | P52: =_xlfn.XLOOKUP(D52,'PRODUCT CATALOGUE'!$A$2:$A$13,'PRODUCT CATALOGUE'!$E$2:$E$13) -> 1600 | Q52: 5600 | R52: =Q52-P52 -> 4000 | S52: =R52/Q52 -> 0.71428571 | T52: =M52*Q52 -> 560 | U52: =IF(S52>100%,"false","good") -> good
A53: TXN052 | B53: 18/02/2026 | C53: EM03 | D53: PR05 | E53: Kefilwe Sithole | F53: -2 | G53: 1200 | I53: RETURNED | J53: =_xlfn.XLOOKUP(C53,'STAFF TABLE'!$A$2:$A$11,'STAFF TABLE'!$B$2:$B$11) -> Zanele Dlamini | K53: =_xlfn.XLOOKUP(C53,'STAFF TABLE'!$A$2:$A$11,'STAFF TABLE'!$C$2:$C$11) -> Cape Town Branch | L53: =_xlfn.XLOOKUP(C53,'STAFF TABLE'!$A$2:$A$11,'STAFF TABLE'!$D$2:$D$11) -> Western Cape | M53: =_xlfn.XLOOKUP(C53,'STAFF TABLE'!$A$2:$A$11,'STAFF TABLE'!$E$2:$E$11) -> 0.09 | N53: =_xlfn.XLOOKUP(D53,'PRODUCT CATALOGUE'!$A$2:$A$13,'PRODUCT CATALOGUE'!$B$2:$B$13) -> Webcam HD | O53: =_xlfn.XLOOKUP(D53,'PRODUCT CATALOGUE'!$A$2:$A$13,'PRODUCT CATALOGUE'!$C$2:$C$13) -> Electronics | P53: =_xlfn.XLOOKUP(D53,'PRODUCT CATALOGUE'!$A$2:$A$13,'PRODUCT CATALOGUE'!$E$2:$E$13) -> 620 | Q53: -2400 | R53: =Q53-P53 -> -3020 | S53: =R53/Q53 -> 1.2583333 | T53: =M53*Q53 -> -216 | U53: =IF(S53>100%,"false","good") -> false
A54: TXN053 | B54: 2026-02-19 | C54: EM01 | D54: PR07 | E54: Sipho Dlamini | F54: 4 | G54: 2100 | H54: 8400 | I54: COMPLETED | J54: =_xlfn.XLOOKUP(C54,'STAFF TABLE'!$A$2:$A$11,'STAFF TABLE'!$B$2:$B$11) -> Thabo Nkosi | K54: =_xlfn.XLOOKUP(C54,'STAFF TABLE'!$A$2:$A$11,'STAFF TABLE'!$C$2:$C$11) -> Sandton Branch | L54: =_xlfn.XLOOKUP(C54,'STAFF TABLE'!$A$2:$A$11,'STAFF TABLE'!$D$2:$D$11) -> Gauteng | M54: =_xlfn.XLOOKUP(C54,'STAFF TABLE'!$A$2:$A$11,'STAFF TABLE'!$E$2:$E$11) -> 0.08 | N54: =_xlfn.XLOOKUP(D54,'PRODUCT CATALOGUE'!$A$2:$A$13,'PRODUCT CATALOGUE'!$B$2:$B$13) -> Mechanical Keyboard | O54: =_xlfn.XLOOKUP(D54,'PRODUCT CATALOGUE'!$A$2:$A$13,'PRODUCT CATALOGUE'!$C$2:$C$13) -> Electronics | P54: =_xlfn.XLOOKUP(D54,'PRODUCT CATALOGUE'!$A$2:$A$13,'PRODUCT CATALOGUE'!$E$2:$E$13) -> 1100 | Q54: 8400 | R54: =Q54-P54 -> 7300 | S54: =R54/Q54 -> 0.86904762 | T54: =M54*Q54 -> 672 | U54: =IF(S54>100%,"false","good") -> good
A55: TXN054 | B55: 2026-02-19 | C55: EM06 | D55: PR02 | E55: David Moyo | F55: 1 | G55: 3200 | H55: 3200 | I55: COMPLETED | J55: =_xlfn.XLOOKUP(C55,'STAFF TABLE'!$A$2:$A$11,'STAFF TABLE'!$B$2:$B$11) -> Lebo Mahlangu | K55: =_xlfn.XLOOKUP(C55,'STAFF TABLE'!$A$2:$A$11,'STAFF TABLE'!$C$2:$C$11) -> Polokwane Branch | L55: =_xlfn.XLOOKUP(C55,'STAFF TABLE'!$A$2:$A$11,'STAFF TABLE'!$D$2:$D$11) -> Limpopo | M55: =_xlfn.XLOOKUP(C55,'STAFF TABLE'!$A$2:$A$11,'STAFF TABLE'!$E$2:$E$11) -> 0.07 | N55: =_xlfn.XLOOKUP(D55,'PRODUCT CATALOGUE'!$A$2:$A$13,'PRODUCT CATALOGUE'!$B$2:$B$13) -> Office Chair | O55: =_xlfn.XLOOKUP(D55,'PRODUCT CATALOGUE'!$A$2:$A$13,'PRODUCT CATALOGUE'!$C$2:$C$13) -> Furniture | P55: =_xlfn.XLOOKUP(D55,'PRODUCT CATALOGUE'!$A$2:$A$13,'PRODUCT CATALOGUE'!$E$2:$E$13) -> 1750 | Q55: 3200 | R55: =Q55-P55 -> 1450 | S55: =R55/Q55 -> 0.453125 | T55: =M55*Q55 -> 224 | U55: =IF(S55>100%,"false","good") -> good
A56: TXN055 | B56: 2026-02-20 | C56: EM05 | D56: PR10 | E56: Priya Pillay | F56: 5 | G56: 650 | H56: 3250 | I56: COMPLETED | J56: =_xlfn.XLOOKUP(C56,'STAFF TABLE'!$A$2:$A$11,'STAFF TABLE'!$B$2:$B$11) -> Amahle Zulu | K56: =_xlfn.XLOOKUP(C56,'STAFF TABLE'!$A$2:$A$11,'STAFF TABLE'!$C$2:$C$11) -> Durban Branch | L56: =_xlfn.XLOOKUP(C56,'STAFF TABLE'!$A$2:$A$11,'STAFF TABLE'!$D$2:$D$11) -> KZN | M56: =_xlfn.XLOOKUP(C56,'STAFF TABLE'!$A$2:$A$11,'STAFF TABLE'!$E$2:$E$11) -> 0.1 | N56: =_xlfn.XLOOKUP(D56,'PRODUCT CATALOGUE'!$A$2:$A$13,'PRODUCT CATALOGUE'!$B$2:$B$13) -> Ergonomic Mouse | O56: =_xlfn.XLOOKUP(D56,'PRODUCT CATALOGUE'!$A$2:$A$13,'PRODUCT CATALOGUE'!$C$2:$C$13) -> Electronics | P56: =_xlfn.XLOOKUP(D56,'PRODUCT CATALOGUE'!$A$2:$A$13,'PRODUCT CATALOGUE'!$E$2:$E$13) -> 310 | Q56: 3250 | R56: =Q56-P56 -> 2940 | S56: =R56/Q56 -> 0.90461538 | T56: =M56*Q56 -> 325 | U56: =IF(S56>100%,"false","good") -> good
A57: TXN056 | B57: 20/02/2026 | C57: EM08 | D57: PR12 | E57: Zanele Mokoena | F57: 20 | G57: 120 | H57: 2400 | I57: COMPLETED | J57: =_xlfn.XLOOKUP(C57,'STAFF TABLE'!$A$2:$A$11,'STAFF TABLE'!$B$2:$B$11) -> Kefilwe Sithole | K57: =_xlfn.XLOOKUP(C57,'STAFF TABLE'!$A$2:$A$11,'STAFF TABLE'!$C$2:$C$11) -> Sandton Branch | L57: =_xlfn.XLOOKUP(C57,'STAFF TABLE'!$A$2:$A$11,'STAFF TABLE'!$D$2:$D$11) -> Gauteng | M57: =_xlfn.XLOOKUP(C57,'STAFF TABLE'!$A$2:$A$11,'STAFF TABLE'!$E$2:$E$11) -> 0.08 | N57: =_xlfn.XLOOKUP(D57,'PRODUCT CATALOGUE'!$A$2:$A$13,'PRODUCT CATALOGUE'!$B$2:$B$13) -> Printer Paper Ream | O57: =_xlfn.XLOOKUP(D57,'PRODUCT CATALOGUE'!$A$2:$A$13,'PRODUCT CATALOGUE'!$C$2:$C$13) -> Stationery | P57: =_xlfn.XLOOKUP(D57,'PRODUCT CATALOGUE'!$A$2:$A$13,'PRODUCT CATALOGUE'!$E$2:$E$13) -> 55 | Q57: 2400 | R57: =Q57-P57 -> 2345 | S57: =R57/Q57 -> 0.97708333 | T57: =M57*Q57 -> 192 | U57: =IF(S57>100%,"false","good") -> good
A58: TXN057 | B58: 2026-02-21 | C58: EM02 | D58: PR01 | E58: Riaan Botha | F58: 1 | G58: 15000 | H58: 15000 | I58: COMPLETED | J58: =_xlfn.XLOOKUP(C58,'STAFF TABLE'!$A$2:$A$11,'STAFF TABLE'!$B$2:$B$11) -> Priya Pillay | K58: =_xlfn.XLOOKUP(C58,'STAFF TABLE'!$A$2:$A$11,'STAFF TABLE'!$C$2:$C$11) -> Durban Branch | L58: =_xlfn.XLOOKUP(C58,'STAFF TABLE'!$A$2:$A$11,'STAFF TABLE'!$D$2:$D$11) -> KZN | M58: =_xlfn.XLOOKUP(C58,'STAFF TABLE'!$A$2:$A$11,'STAFF TABLE'!$E$2:$E$11) -> 0.1 | N58: =_xlfn.XLOOKUP(D58,'PRODUCT CATALOGUE'!$A$2:$A$13,'PRODUCT CATALOGUE'!$B$2:$B$13) -> Gaming Laptop | O58: =_xlfn.XLOOKUP(D58,'PRODUCT CATALOGUE'!$A$2:$A$13,'PRODUCT CATALOGUE'!$C$2:$C$13) -> Electronics | P58: =_xlfn.XLOOKUP(D58,'PRODUCT CATALOGUE'!$A$2:$A$13,'PRODUCT CATALOGUE'!$E$2:$E$13) -> 9800 | Q58: 15000 | R58: =Q58-P58 -> 5200 | S58: =R58/Q58 -> 0.34666667 | T58: =M58*Q58 -> 1500 | U58: =IF(S58>100%,"false","good") -> good
A59: TXN058 | B59: 2026-02-24 | C59: EM09 | D59: PR04 | E59: Amahle Zulu | F59: 1 | G59: 5500 | H59: 5500 | I59: COMPLETED | J59: =_xlfn.XLOOKUP(C59,'STAFF TABLE'!$A$2:$A$11,'STAFF TABLE'!$B$2:$B$11) -> David Moyo | K59: =_xlfn.XLOOKUP(C59,'STAFF TABLE'!$A$2:$A$11,'STAFF TABLE'!$C$2:$C$11) -> Polokwane Branch | L59: =_xlfn.XLOOKUP(C59,'STAFF TABLE'!$A$2:$A$11,'STAFF TABLE'!$D$2:$D$11) -> Limpopo | M59: =_xlfn.XLOOKUP(C59,'STAFF TABLE'!$A$2:$A$11,'STAFF TABLE'!$E$2:$E$11) -> 0.07 | N59: =_xlfn.XLOOKUP(D59,'PRODUCT CATALOGUE'!$A$2:$A$13,'PRODUCT CATALOGUE'!$B$2:$B$13) -> Standing Desk | O59: =_xlfn.XLOOKUP(D59,'PRODUCT CATALOGUE'!$A$2:$A$13,'PRODUCT CATALOGUE'!$C$2:$C$13) -> Furniture | P59: =_xlfn.XLOOKUP(D59,'PRODUCT CATALOGUE'!$A$2:$A$13,'PRODUCT CATALOGUE'!$E$2:$E$13) -> 3100 | Q59: 5500 | R59: =Q59-P59 -> 2400 | S59: =R59/Q59 -> 0.43636364 | T59: =M59*Q59 -> 385 | U59: =IF(S59>100%,"false","good") -> good
A60: TXN059 | B60: 24/02/2026 | C60: EM07 | D60: PR08 | E60: Lebo Mahlangu | F60: 4 | G60: 890 | H60: 3560 | I60: COMPLETED | J60: =_xlfn.XLOOKUP(C60,'STAFF TABLE'!$A$2:$A$11,'STAFF TABLE'!$B$2:$B$11) -> Fatima Patel | K60: =_xlfn.XLOOKUP(C60,'STAFF TABLE'!$A$2:$A$11,'STAFF TABLE'!$C$2:$C$11) -> Cape Town Branch | L60: =_xlfn.XLOOKUP(C60,'STAFF TABLE'!$A$2:$A$11,'STAFF TABLE'!$D$2:$D$11) -> Western Cape | M60: =_xlfn.XLOOKUP(C60,'STAFF TABLE'!$A$2:$A$11,'STAFF TABLE'!$E$2:$E$11) -> 0.09 | N60: =_xlfn.XLOOKUP(D60,'PRODUCT CATALOGUE'!$A$2:$A$13,'PRODUCT CATALOGUE'!$B$2:$B$13) -> Whiteboard | O60: =_xlfn.XLOOKUP(D60,'PRODUCT CATALOGUE'!$A$2:$A$13,'PRODUCT CATALOGUE'!$C$2:$C$13) -> Stationery | P60: =_xlfn.XLOOKUP(D60,'PRODUCT CATALOGUE'!$A$2:$A$13,'PRODUCT CATALOGUE'!$E$2:$E$13) -> 420 | Q60: 3560 | R60: =Q60-P60 -> 3140 | S60: =R60/Q60 -> 0.88202247 | T60: =M60*Q60 -> 320.4 | U60: =IF(S60>100%,"false","good") -> good
A61: TXN060 | B61: 2026-02-25 | C61: EM10 | D61: PR03 | E61: Fatima Patel | F61: 3 | G61: 1800 | H61: 5400 | I61: COMPLETED | J61: =_xlfn.XLOOKUP(C61,'STAFF TABLE'!$A$2:$A$11,'STAFF TABLE'!$B$2:$B$11) -> Sipho Dlamini | K61: =_xlfn.XLOOKUP(C61,'STAFF TABLE'!$A$2:$A$11,'STAFF TABLE'!$C$2:$C$11) -> Durban Branch | L61: =_xlfn.XLOOKUP(C61,'STAFF TABLE'!$A$2:$A$11,'STAFF TABLE'!$D$2:$D$11) -> KZN | M61: =_xlfn.XLOOKUP(C61,'STAFF TABLE'!$A$2:$A$11,'STAFF TABLE'!$E$2:$E$11) -> 0.1 | N61: =_xlfn.XLOOKUP(D61,'PRODUCT CATALOGUE'!$A$2:$A$13,'PRODUCT CATALOGUE'!$B$2:$B$13) -> Wireless Headset | O61: =_xlfn.XLOOKUP(D61,'PRODUCT CATALOGUE'!$A$2:$A$13,'PRODUCT CATALOGUE'!$C$2:$C$13) -> Electronics | P61: =_xlfn.XLOOKUP(D61,'PRODUCT CATALOGUE'!$A$2:$A$13,'PRODUCT CATALOGUE'!$E$2:$E$13) -> 950 | Q61: 5400 | R61: =Q61-P61 -> 4450 | S61: =R61/Q61 -> 0.82407407 | T61: =M61*Q61 -> 540 | U61: =IF(S61>100%,"false","good") -> good
A62: TXN061 | B62: 2026-03-03 | C62: EM01 | D62: PR01 | E62: Nomsa Khumalo | F62: 1 | G62: 15000 | H62: 15000 | I62: COMPLETED | J62: =_xlfn.XLOOKUP(C62,'STAFF TABLE'!$A$2:$A$11,'STAFF TABLE'!$B$2:$B$11) -> Thabo Nkosi | K62: =_xlfn.XLOOKUP(C62,'STAFF TABLE'!$A$2:$A$11,'STAFF TABLE'!$C$2:$C$11) -> Sandton Branch | L62: =_xlfn.XLOOKUP(C62,'STAFF TABLE'!$A$2:$A$11,'STAFF TABLE'!$D$2:$D$11) -> Gauteng | M62: =_xlfn.XLOOKUP(C62,'STAFF TABLE'!$A$2:$A$11,'STAFF TABLE'!$E$2:$E$11) -> 0.08 | N62: =_xlfn.XLOOKUP(D62,'PRODUCT CATALOGUE'!$A$2:$A$13,'PRODUCT CATALOGUE'!$B$2:$B$13) -> Gaming Laptop | O62: =_xlfn.XLOOKUP(D62,'PRODUCT CATALOGUE'!$A$2:$A$13,'PRODUCT CATALOGUE'!$C$2:$C$13) -> Electronics | P62: =_xlfn.XLOOKUP(D62,'PRODUCT CATALOGUE'!$A$2:$A$13,'PRODUCT CATALOGUE'!$E$2:$E$13) -> 9800 | Q62: 15000 | R62: =Q62-P62 -> 5200 | S62: =R62/Q62 -> 0.34666667 | T62: =M62*Q62 -> 1200 | U62: =IF(S62>100%,"false","good") -> good
A63: TXN062 | B63: 03/03/2026 | C63: EM05 | D63: PR09 | E63: Pieter van Wyk | F63: 2 | G63: 4800 | H63: 9600 | I63: COMPLETED | J63: =_xlfn.XLOOKUP(C63,'STAFF TABLE'!$A$2:$A$11,'STAFF TABLE'!$B$2:$B$11) -> Amahle Zulu | K63: =_xlfn.XLOOKUP(C63,'STAFF TABLE'!$A$2:$A$11,'STAFF TABLE'!$C$2:$C$11) -> Durban Branch | L63: =_xlfn.XLOOKUP(C63,'STAFF TABLE'!$A$2:$A$11,'STAFF TABLE'!$D$2:$D$11) -> KZN | M63: =_xlfn.XLOOKUP(C63,'STAFF TABLE'!$A$2:$A$11,'STAFF TABLE'!$E$2:$E$11) -> 0.1 | N63: =_xlfn.XLOOKUP(D63,'PRODUCT CATALOGUE'!$A$2:$A$13,'PRODUCT CATALOGUE'!$B$2:$B$13) -> Monitor 27inch | O63: =_xlfn.XLOOKUP(D63,'PRODUCT CATALOGUE'!$A$2:$A$13,'PRODUCT CATALOGUE'!$C$2:$C$13) -> Electronics | P63: =_xlfn.XLOOKUP(D63,'PRODUCT CATALOGUE'!$A$2:$A$13,'PRODUCT CATALOGUE'!$E$2:$E$13) -> 2900 | Q63: 9600 | R63: =Q63-P63 -> 6700 | S63: =R63/Q63 -> 0.69791667 | T63: =M63*Q63 -> 960 | U63: =IF(S63>100%,"false","good") -> good
A64: TXN063 | B64: 2026-03-04 | C64: EM03 | D64: PR07 | F64: 3 | G64: 2100 | H64: 6300 | I64: COMPLETED | J64: =_xlfn.XLOOKUP(C64,'STAFF TABLE'!$A$2:$A$11,'STAFF TABLE'!$B$2:$B$11) -> Zanele Dlamini | K64: =_xlfn.XLOOKUP(C64,'STAFF TABLE'!$A$2:$A$11,'STAFF TABLE'!$C$2:$C$11) -> Cape Town Branch | L64: =_xlfn.XLOOKUP(C64,'STAFF TABLE'!$A$2:$A$11,'STAFF TABLE'!$D$2:$D$11) -> Western Cape | M64: =_xlfn.XLOOKUP(C64,'STAFF TABLE'!$A$2:$A$11,'STAFF TABLE'!$E$2:$E$11) -> 0.09 | N64: =_xlfn.XLOOKUP(D64,'PRODUCT CATALOGUE'!$A$2:$A$13,'PRODUCT CATALOGUE'!$B$2:$B$13) -> Mechanical Keyboard | O64: =_xlfn.XLOOKUP(D64,'PRODUCT CATALOGUE'!$A$2:$A$13,'PRODUCT CATALOGUE'!$C$2:$C$13) -> Electronics | P64: =_xlfn.XLOOKUP(D64,'PRODUCT CATALOGUE'!$A$2:$A$13,'PRODUCT CATALOGUE'!$E$2:$E$13) -> 1100 | Q64: 6300 | R64: =Q64-P64 -> 5200 | S64: =R64/Q64 -> 0.82539683 | T64: =M64*Q64 -> 567 | U64: =IF(S64>100%,"false","good") -> good
A65: TXN064 | B65: 2026-03-04 | C65: EM08 | D65: PR04 | E65: Sipho Dlamini | F65: 1 | G65: 5500 | H65: 5500 | I65: COMPLETED | J65: =_xlfn.XLOOKUP(C65,'STAFF TABLE'!$A$2:$A$11,'STAFF TABLE'!$B$2:$B$11) -> Kefilwe Sithole | K65: =_xlfn.XLOOKUP(C65,'STAFF TABLE'!$A$2:$A$11,'STAFF TABLE'!$C$2:$C$11) -> Sandton Branch | L65: =_xlfn.XLOOKUP(C65,'STAFF TABLE'!$A$2:$A$11,'STAFF TABLE'!$D$2:$D$11) -> Gauteng | M65: =_xlfn.XLOOKUP(C65,'STAFF TABLE'!$A$2:$A$11,'STAFF TABLE'!$E$2:$E$11) -> 0.08 | N65: =_xlfn.XLOOKUP(D65,'PRODUCT CATALOGUE'!$A$2:$A$13,'PRODUCT CATALOGUE'!$B$2:$B$13) -> Standing Desk | O65: =_xlfn.XLOOKUP(D65,'PRODUCT CATALOGUE'!$A$2:$A$13,'PRODUCT CATALOGUE'!$C$2:$C$13) -> Furniture | P65: =_xlfn.XLOOKUP(D65,'PRODUCT CATALOGUE'!$A$2:$A$13,'PRODUCT CATALOGUE'!$E$2:$E$13) -> 3100 | Q65: 5500 | R65: =Q65-P65 -> 2400 | S65: =R65/Q65 -> 0.43636364 | T65: =M65*Q65 -> 440 | U65: =IF(S65>100%,"false","good") -> good
A66: TXN065 | B66: 2026-03-05 | C66: EM02 | D66: PR06 | E66: David Moyo | F66: 15 | G66: 350 | H66: 5250 | I66: COMPLETED | J66: =_xlfn.XLOOKUP(C66,'STAFF TABLE'!$A$2:$A$11,'STAFF TABLE'!$B$2:$B$11) -> Priya Pillay | K66: =_xlfn.XLOOKUP(C66,'STAFF TABLE'!$A$2:$A$11,'STAFF TABLE'!$C$2:$C$11) -> Durban Branch | L66: =_xlfn.XLOOKUP(C66,'STAFF TABLE'!$A$2:$A$11,'STAFF TABLE'!$D$2:$D$11) -> KZN | M66: =_xlfn.XLOOKUP(C66,'STAFF TABLE'!$A$2:$A$11,'STAFF TABLE'!$E$2:$E$11) -> 0.1 | N66: =_xlfn.XLOOKUP(D66,'PRODUCT CATALOGUE'!$A$2:$A$13,'PRODUCT CATALOGUE'!$B$2:$B$13) -> Notebook Bundle | O66: =_xlfn.XLOOKUP(D66,'PRODUCT CATALOGUE'!$A$2:$A$13,'PRODUCT CATALOGUE'!$C$2:$C$13) -> Stationery | P66: =_xlfn.XLOOKUP(D66,'PRODUCT CATALOGUE'!$A$2:$A$13,'PRODUCT CATALOGUE'!$E$2:$E$13) -> 140 | Q66: 5250 | R66: =Q66-P66 -> 5110 | S66: =R66/Q66 -> 0.97333333 | T66: =M66*Q66 -> 525 | U66: =IF(S66>100%,"false","good") -> good
A67: TXN066 | B67: 2026-03-05 | C67: EM06 | D67: PR02 | E67: Kefilwe Sithole | F67: 2 | G67: 3200 | H67: 6400 | I67: PENDING | J67: =_xlfn.XLOOKUP(C67,'STAFF TABLE'!$A$2:$A$11,'STAFF TABLE'!$B$2:$B$11) -> Lebo Mahlangu | K67: =_xlfn.XLOOKUP(C67,'STAFF TABLE'!$A$2:$A$11,'STAFF TABLE'!$C$2:$C$11) -> Polokwane Branch | L67: =_xlfn.XLOOKUP(C67,'STAFF TABLE'!$A$2:$A$11,'STAFF TABLE'!$D$2:$D$11) -> Limpopo | M67: =_xlfn.XLOOKUP(C67,'STAFF TABLE'!$A$2:$A$11,'STAFF TABLE'!$E$2:$E$11) -> 0.07 | N67: =_xlfn.XLOOKUP(D67,'PRODUCT CATALOGUE'!$A$2:$A$13,'PRODUCT CATALOGUE'!$B$2:$B$13) -> Office Chair | O67: =_xlfn.XLOOKUP(D67,'PRODUCT CATALOGUE'!$A$2:$A$13,'PRODUCT CATALOGUE'!$C$2:$C$13) -> Furniture | P67: =_xlfn.XLOOKUP(D67,'PRODUCT CATALOGUE'!$A$2:$A$13,'PRODUCT CATALOGUE'!$E$2:$E$13) -> 1750 | Q67: 6400 | R67: =Q67-P67 -> 4650 | S67: =R67/Q67 -> 0.7265625 | T67: =M67*Q67 -> 448 | U67: =IF(S67>100%,"false","good") -> good
A68: TXN067 | B68: 05/03/2026 | C68: EM09 | D68: PR10 | E68: Priya Pillay | F68: 4 | G68: 650 | H68: 2600 | I68: COMPLETED | J68: =_xlfn.XLOOKUP(C68,'STAFF TABLE'!$A$2:$A$11,'STAFF TABLE'!$B$2:$B$11) -> David Moyo | K68: =_xlfn.XLOOKUP(C68,'STAFF TABLE'!$A$2:$A$11,'STAFF TABLE'!$C$2:$C$11) -> Polokwane Branch | L68: =_xlfn.XLOOKUP(C68,'STAFF TABLE'!$A$2:$A$11,'STAFF TABLE'!$D$2:$D$11) -> Limpopo | M68: =_xlfn.XLOOKUP(C68,'STAFF TABLE'!$A$2:$A$11,'STAFF TABLE'!$E$2:$E$11) -> 0.07 | N68: =_xlfn.XLOOKUP(D68,'PRODUCT CATALOGUE'!$A$2:$A$13,'PRODUCT CATALOGUE'!$B$2:$B$13) -> Ergonomic Mouse | O68: =_xlfn.XLOOKUP(D68,'PRODUCT CATALOGUE'!$A$2:$A$13,'PRODUCT CATALOGUE'!$C$2:$C$13) -> Electronics | P68: =_xlfn.XLOOKUP(D68,'PRODUCT CATALOGUE'!$A$2:$A$13,'PRODUCT CATALOGUE'!$E$2:$E$13) -> 310 | Q68: 2600 | R68: =Q68-P68 -> 2290 | S68: =R68/Q68 -> 0.88076923 | T68: =M68*Q68 -> 182 | U68: =IF(S68>100%,"false","good") -> good
A69: TXN068 | B69: 2026-03-06 | C69: EM07 | D69: PR03 | E69: Zanele Mokoena | F69: 2 | G69: 1800 | H69: 3600 | I69: COMPLETED | J69: =_xlfn.XLOOKUP(C69,'STAFF TABLE'!$A$2:$A$11,'STAFF TABLE'!$B$2:$B$11) -> Fatima Patel | K69: =_xlfn.XLOOKUP(C69,'STAFF TABLE'!$A$2:$A$11,'STAFF TABLE'!$C$2:$C$11) -> Cape Town Branch | L69: =_xlfn.XLOOKUP(C69,'STAFF TABLE'!$A$2:$A$11,'STAFF TABLE'!$D$2:$D$11) -> Western Cape | M69: =_xlfn.XLOOKUP(C69,'STAFF TABLE'!$A$2:$A$11,'STAFF TABLE'!$E$2:$E$11) -> 0.09 | N69: =_xlfn.XLOOKUP(D69,'PRODUCT CATALOGUE'!$A$2:$A$13,'PRODUCT CATALOGUE'!$B$2:$B$13) -> Wireless Headset | O69: =_xlfn.XLOOKUP(D69,'PRODUCT CATALOGUE'!$A$2:$A$13,'PRODUCT CATALOGUE'!$C$2:$C$13) -> Electronics | P69: =_xlfn.XLOOKUP(D69,'PRODUCT CATALOGUE'!$A$2:$A$13,'PRODUCT CATALOGUE'!$E$2:$E$13) -> 950 | Q69: 3600 | R69: =Q69-P69 -> 2650 | S69: =R69/Q69 -> 0.73611111 | T69: =M69*Q69 -> 324 | U69: =IF(S69>100%,"false","good") -> good
A70: TXN069 | B70: 2026-03-06 | C70: EM04 | D70: PR12 | E70: Riaan Botha | F70: 20 | G70: 120 | H70: 2400 | I70: COMPLETED | J70: =_xlfn.XLOOKUP(C70,'STAFF TABLE'!$A$2:$A$11,'STAFF TABLE'!$B$2:$B$11) -> Riaan Botha | K70: =_xlfn.XLOOKUP(C70,'STAFF TABLE'!$A$2:$A$11,'STAFF TABLE'!$C$2:$C$11) -> Sandton Branch | L70: =_xlfn.XLOOKUP(C70,'STAFF TABLE'!$A$2:$A$11,'STAFF TABLE'!$D$2:$D$11) -> Gauteng | M70: =_xlfn.XLOOKUP(C70,'STAFF TABLE'!$A$2:$A$11,'STAFF TABLE'!$E$2:$E$11) -> 0.08 | N70: =_xlfn.XLOOKUP(D70,'PRODUCT CATALOGUE'!$A$2:$A$13,'PRODUCT CATALOGUE'!$B$2:$B$13) -> Printer Paper Ream | O70: =_xlfn.XLOOKUP(D70,'PRODUCT CATALOGUE'!$A$2:$A$13,'PRODUCT CATALOGUE'!$C$2:$C$13) -> Stationery | P70: =_xlfn.XLOOKUP(D70,'PRODUCT CATALOGUE'!$A$2:$A$13,'PRODUCT CATALOGUE'!$E$2:$E$13) -> 55 | Q70: 2400 | R70: =Q70-P70 -> 2345 | S70: =R70/Q70 -> 0.97708333 | T70: =M70*Q70 -> 192 | U70: =IF(S70>100%,"false","good") -> good
A71: TXN070 | B71: 2026-03-07 | C71: EM10 | D71: PR11 | E71: Amahle Zulu | F71: 1 | G71: 2800 | H71: 2800 | I71: COMPLETED | J71: =_xlfn.XLOOKUP(C71,'STAFF TABLE'!$A$2:$A$11,'STAFF TABLE'!$B$2:$B$11) -> Sipho Dlamini | K71: =_xlfn.XLOOKUP(C71,'STAFF TABLE'!$A$2:$A$11,'STAFF TABLE'!$C$2:$C$11) -> Durban Branch | L71: =_xlfn.XLOOKUP(C71,'STAFF TABLE'!$A$2:$A$11,'STAFF TABLE'!$D$2:$D$11) -> KZN | M71: =_xlfn.XLOOKUP(C71,'STAFF TABLE'!$A$2:$A$11,'STAFF TABLE'!$E$2:$E$11) -> 0.1 | N71: =_xlfn.XLOOKUP(D71,'PRODUCT CATALOGUE'!$A$2:$A$13,'PRODUCT CATALOGUE'!$B$2:$B$13) -> Filing Cabinet | O71: =_xlfn.XLOOKUP(D71,'PRODUCT CATALOGUE'!$A$2:$A$13,'PRODUCT CATALOGUE'!$C$2:$C$13) -> Furniture | P71: =_xlfn.XLOOKUP(D71,'PRODUCT CATALOGUE'!$A$2:$A$13,'PRODUCT CATALOGUE'!$E$2:$E$13) -> 1600 | Q71: 2800 | R71: =Q71-P71 -> 1200 | S71: =R71/Q71 -> 0.42857143 | T71: =M71*Q71 -> 280 | U71: =IF(S71>100%,"false","good") -> good
A72: TXN071 | B72: 07/03/2026 | C72: EM01 | D72: PR08 | E72: Lebo Mahlangu | F72: 3 | G72: 890 | H72: 2670 | I72: COMPLETED | J72: =_xlfn.XLOOKUP(C72,'STAFF TABLE'!$A$2:$A$11,'STAFF TABLE'!$B$2:$B$11) -> Thabo Nkosi | K72: =_xlfn.XLOOKUP(C72,'STAFF TABLE'!$A$2:$A$11,'STAFF TABLE'!$C$2:$C$11) -> Sandton Branch | L72: =_xlfn.XLOOKUP(C72,'STAFF TABLE'!$A$2:$A$11,'STAFF TABLE'!$D$2:$D$11) -> Gauteng | M72: =_xlfn.XLOOKUP(C72,'STAFF TABLE'!$A$2:$A$11,'STAFF TABLE'!$E$2:$E$11) -> 0.08 | N72: =_xlfn.XLOOKUP(D72,'PRODUCT CATALOGUE'!$A$2:$A$13,'PRODUCT CATALOGUE'!$B$2:$B$13) -> Whiteboard | O72: =_xlfn.XLOOKUP(D72,'PRODUCT CATALOGUE'!$A$2:$A$13,'PRODUCT CATALOGUE'!$C$2:$C$13) -> Stationery | P72: =_xlfn.XLOOKUP(D72,'PRODUCT CATALOGUE'!$A$2:$A$13,'PRODUCT CATALOGUE'!$E$2:$E$13) -> 420 | Q72: 2670 | R72: =Q72-P72 -> 2250 | S72: =R72/Q72 -> 0.84269663 | T72: =M72*Q72 -> 213.6 | U72: =IF(S72>100%,"false","good") -> good
A73: TXN072 | B73: 2026-03-10 | C73: EM05 | D73: PR01 | E73: Fatima Patel | F73: 1 | G73: 15000 | H73: 15000 | I73: COMPLETED | J73: =_xlfn.XLOOKUP(C73,'STAFF TABLE'!$A$2:$A$11,'STAFF TABLE'!$B$2:$B$11) -> Amahle Zulu | K73: =_xlfn.XLOOKUP(C73,'STAFF TABLE'!$A$2:$A$11,'STAFF TABLE'!$C$2:$C$11) -> Durban Branch | L73: =_xlfn.XLOOKUP(C73,'STAFF TABLE'!$A$2:$A$11,'STAFF TABLE'!$D$2:$D$11) -> KZN | M73: =_xlfn.XLOOKUP(C73,'STAFF TABLE'!$A$2:$A$11,'STAFF TABLE'!$E$2:$E$11) -> 0.1 | N73: =_xlfn.XLOOKUP(D73,'PRODUCT CATALOGUE'!$A$2:$A$13,'PRODUCT CATALOGUE'!$B$2:$B$13) -> Gaming Laptop | O73: =_xlfn.XLOOKUP(D73,'PRODUCT CATALOGUE'!$A$2:$A$13,'PRODUCT CATALOGUE'!$C$2:$C$13) -> Electronics | P73: =_xlfn.XLOOKUP(D73,'PRODUCT CATALOGUE'!$A$2:$A$13,'PRODUCT CATALOGUE'!$E$2:$E$13) -> 9800 | Q73: 15000 | R73: =Q73-P73 -> 5200 | S73: =R73/Q73 -> 0.34666667 | T73: =M73*Q73 -> 1500 | U73: =IF(S73>100%,"false","good") -> good
A74: TXN073 | B74: 2026-03-10 | C74: EM03 | D74: PR05 | E74: Nomsa Khumalo | F74: 6 | G74: 1200 | H74: 6200 | I74: COMPLETED | J74: =_xlfn.XLOOKUP(C74,'STAFF TABLE'!$A$2:$A$11,'STAFF TABLE'!$B$2:$B$11) -> Zanele Dlamini | K74: =_xlfn.XLOOKUP(C74,'STAFF TABLE'!$A$2:$A$11,'STAFF TABLE'!$C$2:$C$11) -> Cape Town Branch | L74: =_xlfn.XLOOKUP(C74,'STAFF TABLE'!$A$2:$A$11,'STAFF TABLE'!$D$2:$D$11) -> Western Cape | M74: =_xlfn.XLOOKUP(C74,'STAFF TABLE'!$A$2:$A$11,'STAFF TABLE'!$E$2:$E$11) -> 0.09 | N74: =_xlfn.XLOOKUP(D74,'PRODUCT CATALOGUE'!$A$2:$A$13,'PRODUCT CATALOGUE'!$B$2:$B$13) -> Webcam HD | O74: =_xlfn.XLOOKUP(D74,'PRODUCT CATALOGUE'!$A$2:$A$13,'PRODUCT CATALOGUE'!$C$2:$C$13) -> Electronics | P74: =_xlfn.XLOOKUP(D74,'PRODUCT CATALOGUE'!$A$2:$A$13,'PRODUCT CATALOGUE'!$E$2:$E$13) -> 620 | Q74: 7200 | R74: =Q74-P74 -> 6580 | S74: =R74/Q74 -> 0.91388889 | T74: =M74*Q74 -> 648 | U74: =IF(S74>100%,"false","good") -> good
A75: TXN074 | B75: 10/03/2026 | C75: EM08 | D75: PR09 | E75: Pieter van Wyk | F75: 2 | G75: 4800 | H75: 9600 | I75: COMPLETED | J75: =_xlfn.XLOOKUP(C75,'STAFF TABLE'!$A$2:$A$11,'STAFF TABLE'!$B$2:$B$11) -> Kefilwe Sithole | K75: =_xlfn.XLOOKUP(C75,'STAFF TABLE'!$A$2:$A$11,'STAFF TABLE'!$C$2:$C$11) -> Sandton Branch | L75: =_xlfn.XLOOKUP(C75,'STAFF TABLE'!$A$2:$A$11,'STAFF TABLE'!$D$2:$D$11) -> Gauteng | M75: =_xlfn.XLOOKUP(C75,'STAFF TABLE'!$A$2:$A$11,'STAFF TABLE'!$E$2:$E$11) -> 0.08 | N75: =_xlfn.XLOOKUP(D75,'PRODUCT CATALOGUE'!$A$2:$A$13,'PRODUCT CATALOGUE'!$B$2:$B$13) -> Monitor 27inch | O75: =_xlfn.XLOOKUP(D75,'PRODUCT CATALOGUE'!$A$2:$A$13,'PRODUCT CATALOGUE'!$C$2:$C$13) -> Electronics | P75: =_xlfn.XLOOKUP(D75,'PRODUCT CATALOGUE'!$A$2:$A$13,'PRODUCT CATALOGUE'!$E$2:$E$13) -> 2900 | Q75: 9600 | R75: =Q75-P75 -> 6700 | S75: =R75/Q75 -> 0.69791667 | T75: =M75*Q75 -> 768 | U75: =IF(S75>100%,"false","good") -> good
A76: TXN075 | B76: 2026-03-11 | C76: EM02 | D76: PR04 | E76: Riaan Botha | F76: 1 | G76: 5500 | H76: 5500 | I76: COMPLETED | J76: =_xlfn.XLOOKUP(C76,'STAFF TABLE'!$A$2:$A$11,'STAFF TABLE'!$B$2:$B$11) -> Priya Pillay | K76: =_xlfn.XLOOKUP(C76,'STAFF TABLE'!$A$2:$A$11,'STAFF TABLE'!$C$2:$C$11) -> Durban Branch | L76: =_xlfn.XLOOKUP(C76,'STAFF TABLE'!$A$2:$A$11,'STAFF TABLE'!$D$2:$D$11) -> KZN | M76: =_xlfn.XLOOKUP(C76,'STAFF TABLE'!$A$2:$A$11,'STAFF TABLE'!$E$2:$E$11) -> 0.1 | N76: =_xlfn.XLOOKUP(D76,'PRODUCT CATALOGUE'!$A$2:$A$13,'PRODUCT CATALOGUE'!$B$2:$B$13) -> Standing Desk | O76: =_xlfn.XLOOKUP(D76,'PRODUCT CATALOGUE'!$A$2:$A$13,'PRODUCT CATALOGUE'!$C$2:$C$13) -> Furniture | P76: =_xlfn.XLOOKUP(D76,'PRODUCT CATALOGUE'!$A$2:$A$13,'PRODUCT CATALOGUE'!$E$2:$E$13) -> 3100 | Q76: 5500 | R76: =Q76-P76 -> 2400 | S76: =R76/Q76 -> 0.43636364 | T76: =M76*Q76 -> 550 | U76: =IF(S76>100%,"false","good") -> good
... A81: TXN080 | B81: 2026-03-14 | C81: EM10 | D81: PR03 | E81: Pieter van Wyk | F81: 3 | G81: 1800 | H81: 5400 | I81: COMPLETED | J81: =_xlfn.XLOOKUP(C81,'STAFF TABLE'!$A$2:$A$11,'STAFF TABLE'!$B$2:$B$11) -> Sipho Dlamini | K81: =_xlfn.XLOOKUP(C81,'STAFF TABLE'!$A$2:$A$11,'STAFF TABLE'!$C$2:$C$11) -> Durban Branch | L81: =_xlfn.XLOOKUP(C81,'STAFF TABLE'!$A$2:$A$11,'STAFF TABLE'!$D$2:$D$11) -> KZN | M81: =_xlfn.XLOOKUP(C81,'STAFF TABLE'!$A$2:$A$11,'STAFF TABLE'!$E$2:$E$11) -> 0.1 | N81: =_xlfn.XLOOKUP(D81,'PRODUCT CATALOGUE'!$A$2:$A$13,'PRODUCT CATALOGUE'!$B$2:$B$13) -> Wireless Headset | O81: =_xlfn.XLOOKUP(D81,'PRODUCT CATALOGUE'!$A$2:$A$13,'PRODUCT CATALOGUE'!$C$2:$C$13) -> Electronics | P81: =_xlfn.XLOOKUP(D81,'PRODUCT CATALOGUE'!$A$2:$A$13,'PRODUCT CATALOGUE'!$E$2:$E$13) -> 950 | Q81: 5400 | R81: =Q81-P81 -> 4450 | S81: =R81/Q81 -> 0.82407407 | T81: =M81*Q81 -> 540 | U81: =IF(S81>100%,"false","good") -> good

Sheet CLEANED DATA
A2: TxnID | B2: Date | C2: EmpID | D2: ProductID | E2: CustomerName | F2: Quantity | G2: Unit Price (R) | H2: Total Revenue (R) | I2: Status | J2: Rep Name | K2: Branch | L2: Region | M2: Commission Rate | N2: Product Name | O2: Category | P2: Cost Price (R) | Q2: Revenue Check | R2: Profit (R) | S2: Profit Margin % | T2: Commission Earned (R) | U2: Performance Flag
A3: TXN001 | B3: 46027 | C3: EM01 | D3: PR09 | E3: Fatima Patel | F3: 2 | G3: 4800 | H3: 9600 | I3: COMPLETED | J3: Thabo Nkosi | K3: Sandton Branch | L3: Gauteng | M3: 0.08 | N3: Monitor 27inch | O3: Electronics | P3: 2900 | Q3: 9600 | R3: 6700 | S3: 0.69791667 | T3: 768 | U3: good
A4: TXN002 | B4: 46027 | C4: EM03 | D4: PR01 | F4: 1 | G4: 15000 | H4: 15000 | I4: COMPLETED | J4: Zanele Dlamini | K4: Cape Town Branch | L4: Western Cape | M4: 0.09 | N4: Gaming Laptop | O4: Electronics | P4: 9800 | Q4: 15000 | R4: 5200 | S4: 0.34666667 | T4: 1350 | U4: good
A5: TXN003 | B5: 46028 | C5: EM05 | D5: PR07 | E5: Nomsa Khumalo | F5: 3 | G5: 2100 | H5: 6300 | I5: COMPLETED | J5: Amahle Zulu | K5: Durban Branch | L5: KZN | M5: 0.1 | N5: Mechanical Keyboard | O5: Electronics | P5: 1100 | Q5: 6300 | R5: 5200 | S5: 0.82539683 | T5: 630 | U5: good
A6: TXN004 | B6: 46028 | C6: EM02 | D6: PR04 | E6: Pieter van Wyk | F6: 1 | G6: 5500 | H6: 5500 | I6: COMPLETED | J6: Priya Pillay | K6: Durban Branch | L6: KZN | M6: 0.1 | N6: Standing Desk | O6: Furniture | P6: 3100 | Q6: 5500 | R6: 2400 | S6: 0.43636364 | T6: 550 | U6: good
A7: TXN005 | B7: 46029 | C7: EM08 | D7: PR06 | E7: Kefilwe Sithole | F7: 2 | G7: 350 | H7: 700 | I7: COMPLETED | J7: Kefilwe Sithole | K7: Sandton Branch | L7: Gauteng | M7: 0.08 | N7: Notebook Bundle | O7: Stationery | P7: 140 | Q7: 700 | R7: 560 | S7: 0.8 | T7: 56 | U7: good
A8: TXN006 | B8: 46029 | C8: EM06 | D8: PR02 | E8: Sipho Dlamini | F8: 1 | G8: 3200 | H8: 3200 | I8: PENDING | J8: Lebo Mahlangu | K8: Polokwane Branch | L8: Limpopo | M8: 0.07 | N8: Office Chair | O8: Furniture | P8: 1750 | Q8: 3200 | R8: 1450 | S8: 0.453125 | T8: 224 | U8: good
A9: TXN007 | B9: 46029 | C9: EM01 | D9: PR10 | E9: David Moyo | F9: 5 | G9: 650 | H9: 3250 | I9: COMPLETED | J9: Thabo Nkosi | K9: Sandton Branch | L9: Gauteng | M9: 0.08 | N9: Ergonomic Mouse | O9: Electronics | P9: 310 | Q9: 3250 | R9: 2940 | S9: 0.90461538 | T9: 260 | U9: good
A10: TXN008 | B10: 46030 | C10: EM04 | D10: PR03 | E10: Priya Pillay | F10: 4 | G10: 1800 | H10: 7200 | I10: COMPLETED | J10: Riaan Botha | K10: Sandton Branch | L10: Gauteng | M10: 0.08 | N10: Wireless Headset | O10: Electronics | P10: 950 | Q10: 7200 | R10: 6250 | S10: 0.86805556 | T10: 576 | U10: good
A11: TXN009 | B11: 46030 | C11: EM07 | D11: PR01 | E11: Zanele Mokoena | F11: 2 | G11: 15000 | H11: 25000 | I11: COMPLETED | J11: Fatima Patel | K11: Cape Town Branch | L11: Western Cape | M11: 0.09 | N11: Gaming Laptop | O11: Electronics | P11: 9800 | Q11: 30000 | R11: 20200 | S11: 0.67333333 | T11: 2700 | U11: good
A12: TXN010 | B12: 46031 | C12: EM10 | D12: PR08 | F12: 3 | G12: 890 | H12: 2670 | I12: CANCELLED | J12: Sipho Dlamini | K12: Durban Branch | L12: KZN | M12: 0.1 | N12: Whiteboard | O12: Stationery | P12: 420 | Q12: 2670 | R12: 2250 | S12: 0.84269663 | T12: 267 | U12: good
A13: TXN011 | B13: 46031 | C13: EM03 | D13: PR09 | E13: Riaan Botha | F13: 1 | G13: 4800 | H13: 4800 | I13: COMPLETED | J13: Zanele Dlamini | K13: Cape Town Branch | L13: Western Cape | M13: 0.09 | N13: Monitor 27inch | O13: Electronics | P13: 2900 | Q13: 4800 | R13: 1900 | S13: 0.39583333 | T13: 432 | U13: good
A14: TXN012 | B14: 46031 | C14: EM05 | D14: PR12 | E14: Amahle Zulu | F14: 10 | G14: 120 | H14: 1200 | I14: COMPLETED | J14: Amahle Zulu | K14: Durban Branch | L14: KZN | M14: 0.1 | N14: Printer Paper Ream | O14: Stationery | P14: 55 | Q14: 1200 | R14: 1145 | S14: 0.95416667 | T14: 120 | U14: good
A15: TXN013 | B15: 46032 | C15: EM09 | D15: PR11 | E15: Lebo Mahlangu | F15: 1 | G15: 2800 | H15: 2800 | I15: COMPLETED | J15: David Moyo | K15: Polokwane Branch | L15: Limpopo | M15: 0.07 | N15: Filing Cabinet | O15: Furniture | P15: 1600 | Q15: 2800 | R15: 1200 | S15: 0.42857143 | T15: 196 | U15: good
A16: TXN014 | B16: 46032 | C16: EM02 | D16: PR05 | E16: Fatima Patel | F16: 4 | G16: 1200 | H16: 4800 | I16: COMPLETED | J16: Priya Pillay | K16: Durban Branch | L16: KZN | M16: 0.1 | N16: Webcam HD | O16: Electronics | P16: 620 | Q16: 4800 | R16: 4180 | S16: 0.87083333 | T16: 480 | U16: good
A17: TXN015 | B17: 46033 | C17: EM08 | D17: PR01 | E17: Nomsa Khumalo | F17: 1 | G17: 15000 | H17: 15000 | I17: COMPLETED | J17: Kefilwe Sithole | K17: Sandton Branch | L17: Gauteng | M17: 0.08 | N17: Gaming Laptop | O17: Electronics | P17: 9800 | Q17: 15000 | R17: 5200 | S17: 0.34666667 | T17: 1200 | U17: good
A18: TXN016 | B18: 46034 | C18: EM04 | D18: PR04 | E18: Pieter van Wyk | F18: 1 | G18: 5500 | H18: 5500 | I18: COMPLETED | J18: Riaan Botha | K18: Sandton Branch | L18: Gauteng | M18: 0.08 | N18: Standing Desk | O18: Furniture | P18: 3100 | Q18: 5500 | R18: 2400 | S18: 0.43636364 | T18: 440 | U18: good
A19: TXN017 | B19: 46034 | C19: EM06 | D19: PR07 | E19: Kefilwe Sithole | F19: -1 | G19: 2100 | I19: RETURNED | J19: Lebo Mahlangu | K19: Polokwane Branch | L19: Limpopo | M19: 0.07 | N19: Mechanical Keyboard | O19: Electronics | P19: 1100 | Q19: -2100 | R19: -3200 | S19: 1.5238095 | T19: -147 | U19: false
A20: TXN018 | B20: 46035 | C20: EM01 | D20: PR06 | F20: 15 | G20: 350 | H20: 5250 | I20: COMPLETED | J20: Thabo Nkosi | K20: Sandton Branch | L20: Gauteng | M20: 0.08 | N20: Notebook Bundle | O20: Stationery | P20: 140 | Q20: 5250 | R20: 5110 | S20: 0.97333333 | T20: 420 | U20: good
A21: TXN019 | B21: 46035 | C21: em06 | D21: PR03 | E21: Sipho Dlamini | F21: 2 | G21: 1800 | H21: 3600 | I21: COMPLETED | J21: Lebo Mahlangu | K21: Polokwane Branch | L21: Limpopo | M21: 0.07 | N21: Wireless Headset | O21: Electronics | P21: 950 | Q21: 3600 | R21: 2650 | S21: 0.73611111 | T21: 252 | U21: good
A22: TXN020 | B22: 46036 | C22: EM10 | D22: PR09 | E22: David Moyo | F22: 3 | G22: 4800 | H22: 14400 | I22: COMPLETED | J22: Sipho Dlamini | K22: Durban Branch | L22: KZN | M22: 0.1 | N22: Monitor 27inch | O22: Electronics | P22: 2900 | Q22: 14400 | R22: 11500 | S22: 0.79861111 | T22: 1440 | U22: good
A23: TXN021 | B23: 46037 | C23: EM07 | D23: PR02 | E23: Priya Pillay | F23: 2 | G23: 3200 | H23: 6400 | I23: PENDING | J23: Fatima Patel | K23: Cape Town Branch | L23: Western Cape | M23: 0.09 | N23: Office Chair | O23: Furniture | P23: 1750 | Q23: 6400 | R23: 4650 | S23: 0.7265625 | T23: 576 | U23: good
A24: TXN022 | B24: 46037 | C24: EM03 | D24: PR10 | E24: Zanele Mokoena | F24: 6 | G24: 650 | H24: 3900 | I24: COMPLETED | J24: Zanele Dlamini | K24: Cape Town Branch | L24: Western Cape | M24: 0.09 | N24: Ergonomic Mouse | O24: Electronics | P24: 310 | Q24: 3900 | R24: 3590 | S24: 0.92051282 | T24: 351 | U24: good
A25: TXN023 | B25: 46038 | C25: EM05 | D25: PR11 | E25: Riaan Botha | F25: 1 | G25: 2800 | H25: 2800 | I25: COMPLETED | J25: Amahle Zulu | K25: Durban Branch | L25: KZN | M25: 0.1 | N25: Filing Cabinet | O25: Furniture | P25: 1600 | Q25: 2800 | R25: 1200 | S25: 0.42857143 | T25: 280 | U25: good
A26: TXN024 | B26: 46038 | C26: EM08 | D26: PR01 | E26: Amahle Zulu | F26: 2 | G26: 15000 | H26: 28000 | I26: COMPLETED | J26: Kefilwe Sithole | K26: Sandton Branch | L26: Gauteng | M26: 0.08 | N26: Gaming Laptop | O26: Electronics | P26: 9800 | Q26: 30000 | R26: 20200 | S26: 0.67333333 | T26: 2400 | U26: good
A27: TXN025 | B27: 46039 | C27: EM02 | D27: PR08 | E27: Lebo Mahlangu | F27: 4 | G27: 890 | H27: 3560 | I27: COMPLETED | J27: Priya Pillay | K27: Durban Branch | L27: KZN | M27: 0.1 | N27: Whiteboard | O27: Stationery | P27: 420 | Q27: 3560 | R27: 3140 | S27: 0.88202247 | T27: 356 | U27: good
A28: TXN026 | B28: 46041 | C28: EM09 | D28: PR06 | E28: Fatima Patel | F28: 20 | G28: 350 | H28: 7000 | I28: COMPLETED | J28: David Moyo | K28: Polokwane Branch | L28: Limpopo | M28: 0.07 | N28: Notebook Bundle | O28: Stationery | P28: 140 | Q28: 7000 | R28: 6860 | S28: 0.98 | T28: 490 | U28: good
A29: TXN027 | B29: 46041 | C29: EM01 | D29: PR05 | E29: Nomsa Khumalo | F29: 2 | G29: 1200 | H29: 2400 | I29: COMPLETED | J29: Thabo Nkosi | K29: Sandton Branch | L29: Gauteng | M29: 0.08 | N29: Webcam HD | O29: Electronics | P29: 620 | Q29: 2400 | R29: 1780 | S29: 0.74166667 | T29: 192 | U29: good
A30: TXN028 | B30: 46042 | C30: EM04 | D30: PR09 | E30: Pieter van Wyk | F30: 1 | G30: 4800 | H30: N/A | I30: COMPLETED | J30: Riaan Botha | K30: Sandton Branch | L30: Gauteng | M30: 0.08 | N30: Monitor 27inch | O30: Electronics | P30: 2900 | Q30: 4800 | R30: 1900 | S30: 0.39583333 | T30: 384 | U30: good
A31: TXN029 | B31: 46042 | C31: EM07 | D31: PR12 | E31: Kefilwe Sithole | F31: 25 | G31: 120 | H31: 3000 | I31: COMPLETED | J31: Fatima Patel | K31: Cape Town Branch | L31: Western Cape | M31: 0.09 | N31: Printer Paper Ream | O31: Stationery | P31: 55 | Q31: 3000 | R31: 2945 | S31: 0.98166667 | T31: 270 | U31: good
A32: TXN030 | B32: 46043 | C32: EM10 | D32: PR07 | E32: Sipho Dlamini | F32: 2 | G32: 2100 | H32: 4200 | I32: COMPLETED | J32: Sipho Dlamini | K32: Durban Branch | L32: KZN | M32: 0.1 | N32: Mechanical Keyboard | O32: Electronics | P32: 1100 | Q32: 4200 | R32: 3100 | S32: 0.73809524 | T32: 420 | U32: good
A33: TXN031 | B33: 46056 | C33: EM03 | D33: PR01 | E33: David Moyo | F33: 1 | G33: 15000 | H33: 15000 | I33: COMPLETED | J33: Zanele Dlamini | K33: Cape Town Branch | L33: Western Cape | M33: 0.09 | N33: Gaming Laptop | O33: Electronics | P33: 9800 | Q33: 15000 | R33: 5200 | S33: 0.34666667 | T33: 1350 | U33: good
A34: TXN032 | B34: 46056 | C34: EM06 | D34: PR04 | F34: 2 | G34: 5500 | H34: 11000 | I34: COMPLETED | J34: Lebo Mahlangu | K34: Polokwane Branch | L34: Limpopo | M34: 0.07 | N34: Standing Desk | O34: Furniture | P34: 3100 | Q34: 11000 | R34: 7900 | S34: 0.71818182 | T34: 770 | U34: good
A35: TXN033 | B35: 46057 | C35: EM01 | D35: PR03 | E35: Priya Pillay | F35: 3 | G35: 1800 | H35: 5400 | I35: COMPLETED | J35: Thabo Nkosi | K35: Sandton Branch | L35: Gauteng | M35: 0.08 | N35: Wireless Headset | O35: Electronics | P35: 950 | Q35: 5400 | R35: 4450 | S35: 0.82407407 | T35: 432 | U35: good
A36: TXN034 | B36: 46057 | C36: EM05 | D36: PR08 | E36: Zanele Mokoena | F36: 5 | G36: 890 | H36: 4450 | I36: COMPLETED | J36: Amahle Zulu | K36: Durban Branch | L36: KZN | M36: 0.1 | N36: Whiteboard | O36: Stationery | P36: 420 | Q36: 4450 | R36: 4030 | S36: 0.90561798 | T36: 445 | U36: good
A37: TXN035 | B37: 46058 | C37: EM08 | D37: PR09 | E37: Riaan Botha | F37: 2 | G37: 4800 | H37: 9600 | I37: COMPLETED | J37: Kefilwe Sithole | K37: Sandton Branch | L37: Gauteng | M37: 0.08 | N37: Monitor 27inch | O37: Electronics | P37: 2900 | Q37: 9600 | R37: 6700 | S37: 0.69791667 | T37: 768 | U37: good
A38: TXN036 | B38: 46058 | C38: EM02 | D38: PR06 | E38: Amahle Zulu | F38: 12 | G38: 350 | H38: 4200 | I38: COMPLETED | J38: Priya Pillay | K38: Durban Branch | L38: KZN | M38: 0.1 | N38: Notebook Bundle | O38: Stationery | P38: 140 | Q38: 4200 | R38: 4060 | S38: 0.96666667 | T38: 420 | U38: good
A39: TXN037 | B39: 46058 | C39: EM09 | D39: PR01 | E39: Lebo Mahlangu | F39: 1 | G39: 15000 | H39: 15000 | I39: COMPLETED | J39: David Moyo | K39: Polokwane Branch | L39: Limpopo | M39: 0.07 | N39: Gaming Laptop | O39: Electronics | P39: 9800 | Q39: 15000 | R39: 5200 | S39: 0.34666667 | T39: 1050 | U39: good
A40: TXN038 | B40: 46059 | C40: EM07 | D40: PR11 | E40: Fatima Patel | F40: 3 | G40: 2800 | H40: 8400 | I40: COMPLETED | J40: Fatima Patel | K40: Cape Town Branch | L40: Western Cape | M40: 0.09 | N40: Filing Cabinet | O40: Furniture | P40: 1600 | Q40: 8400 | R40: 6800 | S40: 0.80952381 | T40: 756 | U40: good
A41: TXN039 | B41: 46060 | C41: EM04 | D41: PR05 | E41: Nomsa Khumalo | F41: 4 | G41: 1200 | H41: 4800 | I41: COMPLETED | J41: Riaan Botha | K41: Sandton Branch | L41: Gauteng | M41: 0.08 | N41: Webcam HD | O41: Electronics | P41: 620 | Q41: 4800 | R41: 4180 | S41: 0.87083333 | T41: 384 | U41: good
A42: TXN040 | B42: 46060 | C42: EM10 | D42: PR02 | E42: Pieter van Wyk | F42: 1 | G42: 3200 | H42: 3200 | I42: PENDING | J42: Sipho Dlamini | K42: Durban Branch | L42: KZN | M42: 0.1 | N42: Office Chair | O42: Furniture | P42: 1750 | Q42: 3200 | R42: 1450 | S42: 0.453125 | T42: 320 | U42: good
A43: TXN041 | B43: 46063 | C43: EM03 | D43: PR10 | F43: 4 | G43: 650 | H43: 2600 | I43: COMPLETED | J43: Zanele Dlamini | K43: Cape Town Branch | L43: Western Cape | M43: 0.09 | N43: Ergonomic Mouse | O43: Electronics | P43: 310 | Q43: 2600 | R43: 2290 | S43: 0.88076923 | T43: 234 | U43: good
A44: TXN042 | B44: 46063 | C44: EM01 | D44: PR07 | E44: Sipho Dlamini | F44: 3 | G44: 2100 | H44: 6300 | I44: COMPLETED | J44: Thabo Nkosi | K44: Sandton Branch | L44: Gauteng | M44: 0.08 | N44: Mechanical Keyboard | O44: Electronics | P44: 1100 | Q44: 6300 | R44: 5200 | S44: 0.82539683 | T44: 504 | U44: good
A45: TXN043 | B45: 46064 | C45: EM06 | D45: PR12 | E45: David Moyo | F45: 30 | G45: 120 | H45: 3600 | I45: COMPLETED | J45: Lebo Mahlangu | K45: Polokwane Branch | L45: Limpopo | M45: 0.07 | N45: Printer Paper Ream | O45: Stationery | P45: 55 | Q45: 3600 | R45: 3545 | S45: 0.98472222 | T45: 252 | U45: good
A46: TXN044 | B46: 46064 | C46: EM05 | D46: PR09 | E46: Priya Pillay | F46: 2 | G46: 4800 | H46: 9600 | I46: COMPLETED | J46: Amahle Zulu | K46: Durban Branch | L46: KZN | M46: 0.1 | N46: Monitor 27inch | O46: Electronics | P46: 2900 | Q46: 9600 | R46: 6700 | S46: 0.69791667 | T46: 960 | U46: good
A47: TXN045 | B47: 46065 | C47: EM08 | D47: PR01 | E47: Zanele Mokoena | F47: 1 | G47: 15000 | H47: 14000 | I47: COMPLETED | J47: Kefilwe Sithole | K47: Sandton Branch | L47: Gauteng | M47: 0.08 | N47: Gaming Laptop | O47: Electronics | P47: 9800 | Q47: 15000 | R47: 5200 | S47: 0.34666667 | T47: 1200 | U47: good
A48: TXN046 | B48: 46065 | C48: em08 | D48: PR04 | E48: Riaan Botha | F48: 1 | G48: 5500 | H48: 5500 | I48: COMPLETED | J48: Kefilwe Sithole | K48: Sandton Branch | L48: Gauteng | M48: 0.08 | N48: Standing Desk | O48: Furniture | P48: 3100 | Q48: 5500 | R48: 2400 | S48: 0.43636364 | T48: 440 | U48: good
A49: TXN047 | B49: 46065 | C49: EM02 | D49: PR03 | E49: Amahle Zulu | F49: 2 | G49: 1800 | H49: 3600 | I49: COMPLETED | J49: Priya Pillay | K49: Durban Branch | L49: KZN | M49: 0.1 | N49: Wireless Headset | O49: Electronics | P49: 950 | Q49: 3600 | R49: 2650 | S49: 0.73611111 | T49: 360 | U49: good
A50: TXN048 | B50: 46066 | C50: EM09 | D50: PR08 | E50: Lebo Mahlangu | F50: 3 | G50: 890 | H50: 2670 | I50: COMPLETED | J50: David Moyo | K50: Polokwane Branch | L50: Limpopo | M50: 0.07 | N50: Whiteboard | O50: Stationery | P50: 420 | Q50: 2670 | R50: 2250 | S50: 0.84269663 | T50: 186.9 | U50: good
A51: TXN049 | B51: 46067 | C51: EM07 | D51: PR06 | E51: Fatima Patel | F51: 8 | G51: 350 | H51: 2800 | I51: COMPLETED | J51: Fatima Patel | K51: Cape Town Branch | L51: Western Cape | M51: 0.09 | N51: Notebook Bundle | O51: Stationery | P51: 140 | Q51: 2800 | R51: 2660 | S51: 0.95 | T51: 252 | U51: good
A52: TXN050 | B52: 46070 | C52: EM04 | D52: PR09 | E52: Nomsa Khumalo | F52: 3 | G52: 4800 | H52: TBC | I52: COMPLETED | J52: Riaan Botha | K52: Sandton Branch | L52: Gauteng | M52: 0.08 | N52: Monitor 27inch | O52: Electronics | P52: 2900 | Q52: 14400 | R52: 11500 | S52: 0.79861111 | T52: 1152 | U52: good
A53: TXN051 | B53: 46071 | C53: EM10 | D53: PR11 | E53: Pieter van Wyk | F53: 2 | G53: 2800 | H53: 5600 | I53: COMPLETED | J53: Sipho Dlamini | K53: Durban Branch | L53: KZN | M53: 0.1 | N53: Filing Cabinet | O53: Furniture | P53: 1600 | Q53: 5600 | R53: 4000 | S53: 0.71428571 | T53: 560 | U53: good
A54: TXN052 | B54: 46071 | C54: EM03 | D54: PR05 | E54: Kefilwe Sithole | F54: -2 | G54: 1200 | I54: RETURNED | J54: Zanele Dlamini | K54: Cape Town Branch | L54: Western Cape | M54: 0.09 | N54: Webcam HD | O54: Electronics | P54: 620 | Q54: -2400 | R54: -3020 | S54: 1.2583333 | T54: -216 | U54: false
A55: TXN053 | B55: 46072 | C55: EM01 | D55: PR07 | E55: Sipho Dlamini | F55: 4 | G55: 2100 | H55: 8400 | I55: COMPLETED | J55: Thabo Nkosi | K55: Sandton Branch | L55: Gauteng | M55: 0.08 | N55: Mechanical Keyboard | O55: Electronics | P55: 1100 | Q55: 8400 | R55: 7300 | S55: 0.86904762 | T55: 672 | U55: good
A56: TXN054 | B56: 46072 | C56: EM06 | D56: PR02 | E56: David Moyo | F56: 1 | G56: 3200 | H56: 3200 | I56: COMPLETED | J56: Lebo Mahlangu | K56: Polokwane Branch | L56: Limpopo | M56: 0.07 | N56: Office Chair | O56: Furniture | P56: 1750 | Q56: 3200 | R56: 1450 | S56: 0.453125 | T56: 224 | U56: good
A57: TXN055 | B57: 46073 | C57: EM05 | D57: PR10 | E57: Priya Pillay | F57: 5 | G57: 650 | H57: 3250 | I57: COMPLETED | J57: Amahle Zulu | K57: Durban Branch | L57: KZN | M57: 0.1 | N57: Ergonomic Mouse | O57: Electronics | P57: 310 | Q57: 3250 | R57: 2940 | S57: 0.90461538 | T57: 325 | U57: good
A58: TXN056 | B58: 46073 | C58: EM08 | D58: PR12 | E58: Zanele Mokoena | F58: 20 | G58: 120 | H58: 2400 | I58: COMPLETED | J58: Kefilwe Sithole | K58: Sandton Branch | L58: Gauteng | M58: 0.08 | N58: Printer Paper Ream | O58: Stationery | P58: 55 | Q58: 2400 | R58: 2345 | S58: 0.97708333 | T58: 192 | U58: good
A59: TXN057 | B59: 46074 | C59: EM02 | D59: PR01 | E59: Riaan Botha | F59: 1 | G59: 15000 | H59: 15000 | I59: COMPLETED | J59: Priya Pillay | K59: Durban Branch | L59: KZN | M59: 0.1 | N59: Gaming Laptop | O59: Electronics | P59: 9800 | Q59: 15000 | R59: 5200 | S59: 0.34666667 | T59: 1500 | U59: good
A60: TXN058 | B60: 46077 | C60: EM09 | D60: PR04 | E60: Amahle Zulu | F60: 1 | G60: 5500 | H60: 5500 | I60: COMPLETED | J60: David Moyo | K60: Polokwane Branch | L60: Limpopo | M60: 0.07 | N60: Standing Desk | O60: Furniture | P60: 3100 | Q60: 5500 | R60: 2400 | S60: 0.43636364 | T60: 385 | U60: good
A61: TXN059 | B61: 46077 | C61: EM07 | D61: PR08 | E61: Lebo Mahlangu | F61: 4 | G61: 890 | H61: 3560 | I61: COMPLETED | J61: Fatima Patel | K61: Cape Town Branch | L61: Western Cape | M61: 0.09 | N61: Whiteboard | O61: Stationery | P61: 420 | Q61: 3560 | R61: 3140 | S61: 0.88202247 | T61: 320.4 | U61: good
A62: TXN060 | B62: 46078 | C62: EM10 | D62: PR03 | E62: Fatima Patel | F62: 3 | G62: 1800 | H62: 5400 | I62: COMPLETED | J62: Sipho Dlamini | K62: Durban Branch | L62: KZN | M62: 0.1 | N62: Wireless Headset | O62: Electronics | P62: 950 | Q62: 5400 | R62: 4450 | S62: 0.82407407 | T62: 540 | U62: good
A63: TXN061 | B63: 46084 | C63: EM01 | D63: PR01 | E63: Nomsa Khumalo | F63: 1 | G63: 15000 | H63: 15000 | I63: COMPLETED | J63: Thabo Nkosi | K63: Sandton Branch | L63: Gauteng | M63: 0.08 | N63: Gaming Laptop | O63: Electronics | P63: 9800 | Q63: 15000 | R63: 5200 | S63: 0.34666667 | T63: 1200 | U63: good
A64: TXN062 | B64: 46084 | C64: EM05 | D64: PR09 | E64: Pieter van Wyk | F64: 2 | G64: 4800 | H64: 9600 | I64: COMPLETED | J64: Amahle Zulu | K64: Durban Branch | L64: KZN | M64: 0.1 | N64: Monitor 27inch | O64: Electronics | P64: 2900 | Q64: 9600 | R64: 6700 | S64: 0.69791667 | T64: 960 | U64: good
A65: TXN063 | B65: 46085 | C65: EM03 | D65: PR07 | F65: 3 | G65: 2100 | H65: 6300 | I65: COMPLETED | J65: Zanele Dlamini | K65: Cape Town Branch | L65: Western Cape | M65: 0.09 | N65: Mechanical Keyboard | O65: Electronics | P65: 1100 | Q65: 6300 | R65: 5200 | S65: 0.82539683 | T65: 567 | U65: good
A66: TXN064 | B66: 46085 | C66: EM08 | D66: PR04 | E66: Sipho Dlamini | F66: 1 | G66: 5500 | H66: 5500 | I66: COMPLETED | J66: Kefilwe Sithole | K66: Sandton Branch | L66: Gauteng | M66: 0.08 | N66: Standing Desk | O66: Furniture | P66: 3100 | Q66: 5500 | R66: 2400 | S66: 0.43636364 | T66: 440 | U66: good
A67: TXN065 | B67: 46086 | C67: EM02 | D67: PR06 | E67: David Moyo | F67: 15 | G67: 350 | H67: 5250 | I67: COMPLETED | J67: Priya Pillay | K67: Durban Branch | L67: KZN | M67: 0.1 | N67: Notebook Bundle | O67: Stationery | P67: 140 | Q67: 5250 | R67: 5110 | S67: 0.97333333 | T67: 525 | U67: good
A68: TXN066 | B68: 46086 | C68: EM06 | D68: PR02 | E68: Kefilwe Sithole | F68: 2 | G68: 3200 | H68: 6400 | I68: PENDING | J68: Lebo Mahlangu | K68: Polokwane Branch | L68: Limpopo | M68: 0.07 | N68: Office Chair | O68: Furniture | P68: 1750 | Q68: 6400 | R68: 4650 | S68: 0.7265625 | T68: 448 | U68: good
A69: TXN067 | B69: 46086 | C69: EM09 | D69: PR10 | E69: Priya Pillay | F69: 4 | G69: 650 | H69: 2600 | I69: COMPLETED | J69: David Moyo | K69: Polokwane Branch | L69: Limpopo | M69: 0.07 | N69: Ergonomic Mouse | O69: Electronics | P69: 310 | Q69: 2600 | R69: 2290 | S69: 0.88076923 | T69: 182 | U69: good
A70: TXN068 | B70: 46087 | C70: EM07 | D70: PR03 | E70: Zanele Mokoena | F70: 2 | G70: 1800 | H70: 3600 | I70: COMPLETED | J70: Fatima Patel | K70: Cape Town Branch | L70: Western Cape | M70: 0.09 | N70: Wireless Headset | O70: Electronics | P70: 950 | Q70: 3600 | R70: 2650 | S70: 0.73611111 | T70: 324 | U70: good
A71: TXN069 | B71: 46087 | C71: EM04 | D71: PR12 | E71: Riaan Botha | F71: 20 | G71: 120 | H71: 2400 | I71: COMPLETED | J71: Riaan Botha | K71: Sandton Branch | L71: Gauteng | M71: 0.08 | N71: Printer Paper Ream | O71: Stationery | P71: 55 | Q71: 2400 | R71: 2345 | S71: 0.97708333 | T71: 192 | U71: good
A72: TXN070 | B72: 46088 | C72: EM10 | D72: PR11 | E72: Amahle Zulu | F72: 1 | G72: 2800 | H72: 2800 | I72: COMPLETED | J72: Sipho Dlamini | K72: Durban Branch | L72: KZN | M72: 0.1 | N72: Filing Cabinet | O72: Furniture | P72: 1600 | Q72: 2800 | R72: 1200 | S72: 0.42857143 | T72: 280 | U72: good
A73: TXN071 | B73: 46088 | C73: EM01 | D73: PR08 | E73: Lebo Mahlangu | F73: 3 | G73: 890 | H73: 2670 | I73: COMPLETED | J73: Thabo Nkosi | K73: Sandton Branch | L73: Gauteng | M73: 0.08 | N73: Whiteboard | O73: Stationery | P73: 420 | Q73: 2670 | R73: 2250 | S73: 0.84269663 | T73: 213.6 | U73: good
A74: TXN072 | B74: 46091 | C74: EM05 | D74: PR01 | E74: Fatima Patel | F74: 1 | G74: 15000 | H74: 15000 | I74: COMPLETED | J74: Amahle Zulu | K74: Durban Branch | L74: KZN | M74: 0.1 | N74: Gaming Laptop | O74: Electronics | P74: 9800 | Q74: 15000 | R74: 5200 | S74: 0.34666667 | T74: 1500 | U74: good
A75: TXN073 | B75: 46091 | C75: EM03 | D75: PR05 | E75: Nomsa Khumalo | F75: 6 | G75: 1200 | H75: 6200 | I75: COMPLETED | J75: Zanele Dlamini | K75: Cape Town Branch | L75: Western Cape | M75: 0.09 | N75: Webcam HD | O75: Electronics | P75: 620 | Q75: 7200 | R75: 6580 | S75: 0.91388889 | T75: 648 | U75: good
A76: TXN074 | B76: 46091 | C76: EM08 | D76: PR09 | E76: Pieter van Wyk | F76: 2 | G76: 4800 | H76: 9600 | I76: COMPLETED | J76: Kefilwe Sithole | K76: Sandton Branch | L76: Gauteng | M76: 0.08 | N76: Monitor 27inch | O76: Electronics | P76: 2900 | Q76: 9600 | R76: 6700 | S76: 0.69791667 | T76: 768 | U76: good
A77: TXN075 | B77: 46092 | C77: EM02 | D77: PR04 | E77: Riaan Botha | F77: 1 | G77: 5500 | H77: 5500 | I77: COMPLETED | J77: Priya Pillay | K77: Durban Branch | L77: KZN | M77: 0.1 | N77: Standing Desk | O77: Furniture | P77: 3100 | Q77: 5500 | R77: 2400 | S77: 0.43636364 | T77: 550 | U77: good
... A82: TXN080 | B82: 46095 | C82: EM10 | D82: PR03 | E82: Pieter van Wyk | F82: 3 | G82: 1800 | H82: 5400 | I82: COMPLETED | J82: Sipho Dlamini | K82: Durban Branch | L82: KZN | M82: 0.1 | N82: Wireless Headset | O82: Electronics | P82: 950 | Q82: 5400 | R82: 4450 | S82: 0.82407407 | T82: 540 | U82: good

Sheet BOARD REPORT
A1: Q1 2026 BUSINESS PERFORMANCE REPORT — BOARD PRESENTATION
A2: Prepared by: Anotida Kanzara | C2: Date: 5/17/2026
A3: Period: January – March 2026 | C3: Status: DRAFT
A5: EXECUTIVE SUMMARY
A6: Total Q1 Revenue (R): 499 030.00 | C6: Total Transactions: 80
A7: Best Performing Branch: Sandton Branch | C7: Top Sales Rep: Kefilwe Sithole
A8: Best Selling Category: Electronics | C8: Total Commission Paid (R): 32 316
A9: Total Profit (R):335 345.00 | C9: Avg Profit Margin %: 62
A11: SECTION 1 — REVENUE BY BRANCH
A12: Branch | B12: Total Transactions | C12: Total Revenue (R) | D12: Total Profit (R) | E12: % of Total Revenue
A13: Sandton Branch | B13: 25 | C13: 171720 | D13: 124150 | E13: =D13/C13 -> 0.72297927
A14: Durban Branch | B14: 24 | C14: 143280 | D14: 94655 | E14: =D14/C14 -> 0.66062954
A15: Cape Town Branch | B15: 16 | C15: 110060 | D15: 73345 | E15: =D15/C15 -> 0.66640923
A16: Polokwane Branch | B16: 15 | C16: 73970 | D16: 43195 | E16: =D16/C16 -> 0.58395295
A17: GRAND TOTAL | B17: 80 | C17: 499030 | D17: 335345 | E17: =D17/C17 -> 0.67199367
A19: SECTION 2 — REVENUE BY PRODUCT CATEGORY
A20: Category | B20: Total Transactions | C20: Total Revenue (R) | D20: Avg Order Value (R) | E20: % of Total Revenue
A21: Electronics | B21: 44 | C21: 346150 | D21: 230400 | E21: =D21/C21 -> 0.6656074
A22: Furniture | B22: 18 | C22: 92000 | D22: 71700 | E22: =D22/C22 -> 0.77934783
A23: Stationery | B23: 18 | C23: 60880 | D23: 8390 | E23: =D23/C23 -> 0.13781209
A24: GRAND TOTAL | B24: 80 | C24: 499030 | D24: 310490 | E24: =D24/C24 -> 0.62218704
A26: SECTION 3 — TOP SALES REPS
A27: Rep Name | B27: Branch | C27: Total Revenue (R) | D27: Commission Earned (R) | E27: Performance Flag
A28: Kefilwe Sithole | B28: Sandton Branch | C28: 90300 | D28: 7464 | E28: Good
A29: Thabo Nkosi | B29: Sandton Branch | C29: 58270 | D29: 4661.6 | E29: Good
A30: Fatima Patel | B30: Cape Town Branch | C30: 56260 | D30: 5513.4 | E30: Good
A31: Zanele Dlamini | B31: Cape Town Branch | C31: 53800 | D31: 4716 | E31: Needs Investigation
A32: Amahle Zulu | B32: Durban Branch | C32: 52200 | D32: 5220 | E32: Good
A33: Priya Pillay | B33: Durban Branch | C33: 47410 | D33: 4741 | E33: Good
A34: SECTION 4 — MONTHLY REVENUE TREND
A35: Month | B35: Total Transactions | C35: Total Revenue (R) | D35: Month-on-Month Change
A36: January 2026 | B36: 30 | C36: 197030 | D36: 197030
A37: February 2026 | B37: 30 | C37: 184030 | D37: =C37-C36/C37 -> 184028.93
A38: March 2026 | B38: 20 | C38: 117970 | D38: =C38-C37/C38 -> 117968.44
A40: SECTION 5 — ORDERS REQUIRING INVESTIGATION
A41: TxnID | B41: Issue | C41: Action Required | D41: Assigned To | E41: Priority
A42: TXN009 | B42: Revenue mismatch recorded vs correct | C42: Verify with sales rep | E42: High
A43: TXN017 | B43: Negative quantity — possible return | C43: Confirm with manager | E43: Medium
A44: TXN024 | B44: Revenue mismatch recorded vs correct | C44: Verify with sales rep | E44: High
A45: TXN028 | B45: Revenue shows N/A | C45: Get correct figure from rep | E45: High
A46: TXN045 | B46: Revenue mismatch recorded vs correct | C46: Verify with sales rep | E46: High
A47: TXN050 | B47: Revenue shows TBC | C47: Get correct figure from rep | E47: High
A48: TXN052 | B48: Negative quantity — possible return | C48: Confirm with manager | E48: Medium
A49: TXN073 | B49: Revenue mismatch recorded vs correct | C49: Verify with sales rep | E49: High
A50: Rows 8,16,38,47,69 | B50: Missing customer name | C50: Identify from order system | E50: Medium
A52: CHARTS GO BELOW THIS ROW
A53: Insert: Bar Chart (Branch Revenue) | Pie Chart (Category Split) | Bar Chart (Top Reps) | Line Chart (Monthly Trend)
